Workbook

Sheet Test 4-Stats
A1: Supplier Name | B1: Month | C1: Business Unit | D1: Division/Depot/Department | E1: Cost Centre | F1: Area | G1: Province | H1: Responsible Manager | I1: RFQ Sent Date | J1: Quotes Received Date | K1: Actual Quotation Days | L1: Target Quotation Days | M1: Variance for Quote Days | N1: Approval of best Quote Date | O1: Vehicle Delivery Date | P1: Actual Delivery Days | Q1: Target Delivery Days | R1: Variance for Delivery Days | S1: Reg No | T1: Contract No | U1: Contract Type | V1: Rate Category | W1: Make | X1: Model | Y1: Year | Z1: Fuel Type | AA1: Engine Capacity | AB1: Tyres Allocated | AC1: Tyres Used | AD1: Retail Price | AE1: Discount Amount | AF1: Discount % | AG1: Accessory Amount | AH1: Finance Sundries | AI1: Interest % | AJ1: Residual Value | AK1: RV % | AL1: Start Date | AM1: End Date | AN1: Contract Period | AO1: Inclusive KM per Month | AP1: Total Contract KM | AQ1: Licence Expiry Date | AR1: Odo Start | AS1: Odo End | AT1: KM Travelled | AU1: KM Travelled LTD | AV1: Average LTD Km | AW1: Fixed Rental | AX1: Repairs and Maintenance | AY1: Licence Fee | AZ1: Tracking Cost and Services | BA1: Admin Fee | BB1: Total Fixed Rental (Excl. VAT) | BC1: VAT | BD1: Total Fixed Rental (Incl. VAT) | BE1: Start Date of Excess Billing | BF1: End Date of Excess Billing | BG1: Start Odo of Excess Billing | BH1: End Odo of Excess Billing | BI1: Total KM Travelled | BJ1: Allowed KM | BK1: Excess KM Travelled | BL1: Excess RM (CPK) | BM1: Excess RV (CPK) | BN1: Excess RM Amount | BO1: Excess RV Amount | BP1: Total Excess Amount Excl VAT | BQ1: VAT | BR1: Total Excess Amount Incl VAT | BS1: Operator Default | BT1: Accident and Write Offs | BU1: Tyres | BV1: Additional Costs | BW1: Auxiliary Amount | BX1: OOCP | BY1: Fuel Cost | BZ1: Fuel Litres | CA1: Oil Cost | CB1: Oil Litres | CC1: Monthly Fines Cost | CD1: Monthly E-Toll Cost | CE1: Subtotal Variable Cost | CF1: VAT | CG1: Total Variable Cost | CH1: Total Cost Incl VAT | CI1: Input VAT | CJ1: Total Cost excl Input VAT | CK1: CPK TCO | CL1: Maintenance Days | CM1: Accidents Days | CN1: Breakdowns Days | CO1: Total Availability % | CP1: Restructured Contract End Date | CQ1: Restructured Contract Period | CR1: Restructured Inclusive KM per Month | CS1: Fixed Rental Prior to Restructure | CT1: Overs and Unders (Incl 5% Tolerance) | CU1: Estimated Replacement Date Time & KM | CV1: Estimated Replacement Time | CW1: Estimated Replacement KM | CX1: Deal Status | CY1: Supplier Responsible Name | CZ1: Excess RM YTD | DA1: Excess RV YTD | DB1: Under Utilisation RM YTD | DC1: Under Utilisation RM (CPK) | DD1: Total Under Utilisation RM Amount Excl VAT | DE1: Total Under Utilisation Amount Incl VAT | DF1: Date Sold
A2: Company A | B2: 43831 | C2: Business Unit 1 | D2: Division 1 | E2: Cost Centre 1 | F2: CAPE TOWN | G2: WESTERN CAPE | H2: Manager 1 | I2: 43831 | J2: 43832 | K2: =J2-I2 -> 1 | L2: 1 | M2: =K2-L2 -> 0 | N2: 43845 | O2: 43886 | P2: =O2-N2 -> 41 | Q2: 90 | R2: =P2-Q2 -> -49 | S2: Reg 1 | T2: Contract 1 | U2: Long Term | V2: HALF TON LDV | W2: NISSAN | X2: NP200 1.6 8V AC SAFETY PACK | Y2: 2020 | Z2: PETROL | AA2: 1598 | AB2: 12 | AC2: 0 | AD2: 172956.52 | AE2: 45491.46 | AF2: 0.26 | AG2: 18280.53 | AH2: 584 | AI2: 7.75 | AJ2: 72642 | AK2: 42 | AL2: 43886 | AM2: 45713 | AN2: 60 | AO2: 1500 | AP2: 90000 | AQ2: 46081 | AR2: 32857 | AS2: 33259 | AT2: 402 | AU2: 31765 | AV2: 521 | AW2: 2588.24 | AX2: 566.41 | AY2: 51.41 | AZ2: 300.83 | BA2: 1149.95 | BB2: 4656.84 | BC2: 698.53 | BD2: 5355.37 | BE2: 45748 | BF2: 45838 | BG2: 30301 | BH2: 33259 | BI2: 2958 | BJ2: 4500 | BK2: -1542 | BL2: 0.44 | BM2: 1.4 | BN2: 0 | BO2: 0 | BP2: 0 | BQ2: -87.89 | BR2: 0 | BS2: 0 | BT2: 0 | BU2: 0 | BV2: 0 | BW2: 0 | BX2: 0 | BY2: 1851.3 | BZ2: 0 | CA2: 0 | CB2: 0 | CC2: 0 | CD2: 0 | CE2: 0 | CF2: 0 | CG2: 0 | CH2: 4681.52 | CI2: 610.64 | CJ2: 4070.88 | CK2: 10.13 | CL2: 0 | CM2: 0 | CN2: 0 | CO2: 89.7058 | CQ2: 0 | CR2: 0 | CS2: 0 | CT2: -59735 | CU2: 45808 | CV2: 45808 | CW2: 91494 | CX2: Active | CY2: Name 1 | CZ2: 142.8 | DA2: 462.4 | DB2: -20175.66 | DC2: 0.38 | DD2: -585.96 | DE2: -673.85
A3: Company A | B3: 43831 | C3: Business Unit 2 | D3: Division 2 | E3: Cost Centre 2 | F3: ISANDO | G3: GAUTENG | H3: Manager 2 | I3: 43832 | J3: 43834 | K3: =J3-I3 -> 2 | L3: 1 | M3: =K3-L3 -> 1 | N3: 43846 | O3: 43977 | P3: =O3-N3 -> 131 | Q3: 90 | R3: =P3-Q3 -> 41 | S3: Reg 2 | T3: Contract 2 | U3: Long Term | V3: ONE TON LDV SINGLE CAB | W3: ISUZU | X3: KB 250 D-TEQ FLEETSIDE (SAFETY) | Y3: 2019 | Z3: DIESEL | AA3: 2498 | AB3: 12 | AC3: 12 | AD3: 279652.17 | AE3: 52153.09 | AF3: 0.19 | AG3: 19390.1 | AH3: 1466 | AI3: 7.75 | AL3: 43977 | AM3: 45803 | AN3: 60 | AO3: 2500 | AP3: 170148 | AQ3: 45900 | AR3: 169892 | AS3: 170185 | AT3: 293 | AU3: 170148 | AV3: 2540 | AW3: 3706.98 | AX3: 1730.7 | AY3: 80.85 | AZ3: 581.1 | BA3: 533.83 | BB3: 6633.46 | BC3: 995.02 | BD3: 7628.48 | BE3: 45748 | BF3: 45832 | BG3: 169870 | BH3: 170185 | BI3: 315 | BJ3: 7500 | BK3: -7185 | BL3: 0.79 | BM3: 1.19 | BN3: 0 | BO3: 0 | BP3: 0 | BQ3: -743.65 | BR3: 0 | BS3: 30544.6 | BT3: 0 | BU3: 0 | BV3: 0 | BW3: 0 | BX3: 0 | BY3: 0 | BZ3: 0 | CA3: 0 | CB3: 0 | CC3: 0 | CD3: 0 | CE3: 30544.6 | CF3: 4581.69 | CG3: 35126.29 | CH3: 37053.47 | CI3: 4833.06 | CJ3: 32220.41 | CK3: 109.97 | CL3: 65 | CM3: 0 | CN3: 0 | CO3: 99.5721 | CQ3: 0 | CR3: 0 | CS3: 0 | CT3: 148 | CU3: 45832 | CV3: 45832 | CW3: 170185 | CX3: Active | CY3: Name 1 | CZ3: 37818.93 | DA3: 25067.17 | DB3: -24150.07 | DC3: 0.69 | DD3: -4957.65 | DE3: -5701.3
A4: Company A | B4: 43831 | C4: Business Unit 3 | D4: Division 3 | E4: Cost Centre 3 | F4: PRETORIA | G4: KWAZULU NATAL | H4: Manager 3 | I4: 43833 | J4: 43834 | K4: =J4-I4 -> 1 | L4: 1 | M4: =K4-L4 -> 0 | N4: 43847 | O4: 43917 | P4: =O4-N4 -> 70 | Q4: 90 | R4: =P4-Q4 -> -20 | S4: Reg 3 | T4: Contract 3 | U4: Long Term | V4: ONE TON LDV SINGLE CAB | W4: ISUZU | X4: KB 250 D-TEQ FLEETSIDE (SAFETY) | Y4: 2019 | Z4: DIESEL | AA4: 2498 | AB4: 12 | AC4: 8 | AD4: 279652.17 | AE4: 52288.09 | AF4: 0.19 | AG4: 37811.82 | AH4: 1466 | AI4: 7.75 | AJ4: 115469.58 | AK4: 98.98 | AL4: 43917 | AM4: 45743 | AN4: 60 | AO4: 3000 | AP4: 151634 | AQ4: 45930 | AR4: 149951 | AS4: 151945 | AT4: 1994 | AU4: 151857 | AV4: 2267 | AW4: 3203.39 | AX4: 2068 | AY4: 106.88 | AZ4: 581.1 | BA4: 533.83 | BB4: 6493.2 | BC4: 973.98 | BD4: 7467.18 | BE4: 45748 | BF4: 45838 | BG4: 147088 | BH4: 151945 | BI4: 4857 | BJ4: 9000 | BK4: -4143 | BL4: 0.79 | BM4: 1.19 | BN4: 0 | BO4: 0 | BP4: 0 | BQ4: -428.8 | BR4: 0 | BS4: 0 | BT4: 0 | BU4: 0 | BV4: 0 | BW4: 0 | BX4: 0 | BY4: 5962.26 | BZ4: 0 | CA4: 0 | CB4: 0 | CC4: 0 | CD4: 0 | CE4: 0 | CF4: 0 | CG4: 0 | CH4: 4179.71 | CI4: 545.18 | CJ4: 3634.53 | CK4: 1.82 | CL4: 0 | CM4: 0 | CN4: 0 | CO4: 99.6323 | CQ4: 0 | CR4: 0 | CS4: 0 | CT4: -40143 | CU4: 45808 | CV4: 45808 | CW4: 151722 | CX4: Active | CY4: Name 1 | CZ4: 3924.36 | DA4: 2576.6 | DB4: -27866.48 | DC4: 0.69 | DD4: -2858.67 | DE4: -3287.47
A5: Company B | B5: 43831 | C5: Business Unit 1 | D5: Division 1 | E5: Cost Centre 1 | F5: ISANDO | G5: GAUTENG | H5: Manager 1 | I5: 43834 | J5: 43840 | K5: =J5-I5 -> 6 | L5: 1 | M5: =K5-L5 -> 5 | N5: 43848 | O5: 44040 | P5: =O5-N5 -> 192 | Q5: 90 | R5: =P5-Q5 -> 102 | S5: Reg 4 | T5: Contract 4 | U5: Long Term | V5: ONE TON LDV DOUBLE CAB | W5: ISUZU | X5: KB 250 D-TEQ HI-RIDER D/CAB | Y5: 2019 | Z5: DIESEL | AA5: 2498 | AB5: 12 | AC5: 10 | AD5: 323947.37 | AE5: 38803.67 | AF5: 0.12 | AG5: 18702.72 | AH5: 1646 | AI5: 7.75 | AL5: 44040 | AM5: 45866 | AN5: 60 | AO5: 2500 | AP5: 186410 | AQ5: 45930 | AR5: 176763 | AS5: 186447 | AT5: 9684 | AU5: 186410 | AV5: 2913 | AW5: 2529.37 | AX5: 1951 | AY5: 97.35 | AZ5: 581.1 | BA5: 922.75 | BB5: 6081.57 | BC5: 912.24 | BD5: 6993.81 | BE5: 45748 | BF5: 45834 | BG5: 173188 | BH5: 186447 | BI5: 13259 | BJ5: 7500 | BK5: 5759 | BL5: 0.89 | BM5: 1.36 | BN5: 5125.51 | BO5: 7832.24 | BP5: 12957.75 | BQ5: 1943.66 | BR5: 14901.41 | BS5: 0 | BT5: 0 | BU5: 0 | BV5: 0 | BW5: 0 | BX5: 0 | BY5: 8829.38 | BZ5: 0 | CA5: 0 | CB5: 0 | CC5: 0 | CD5: 0 | CE5: 0 | CF5: 0 | CG5: 0 | CH5: 21895.22 | CI5: 2855.9 | CJ5: 19039.32 | CK5: 1.97 | CL5: 0 | CM5: 0 | CN5: 0 | CO5: 84.2391 | CQ5: 0 | CR5: 0 | CS5: 0 | CT5: 23910 | CU5: 45834 | CV5: 45834 | CW5: 186447 | CX5: Active | CY5: Name 1 | CZ5: 38484.78 | DA5: 30354.48 | DB5: -8261.8 | DC5: 0.78 | DD5: 0 | DE5: 0
A6: Company B | B6: 43831 | C6: Business Unit 2 | D6: Division 2 | E6: Cost Centre 2 | F6: ISANDO | G6: GAUTENG | H6: Manager 2 | I6: 43835 | J6: 43836 | K6: =J6-I6 -> 1 | L6: 1 | M6: =K6-L6 -> 0 | N6: 43849 | O6: 43859 | P6: =O6-N6 -> 10 | Q6: 90 | R6: =P6-Q6 -> -80 | S6: Reg 5 | T6: Contract 5 | U6: Long Term | V6: ONE TON LDV SINGLE CAB | W6: ISUZU | X6: KB 250 D-TEQ FLEETSIDE (SAFETY) | Y6: 2019 | Z6: DIESEL | AA6: 2498 | AB6: 12 | AC6: 10 | AD6: 279652.17 | AE6: 52288.09 | AF6: 0.19 | AG6: 19785.12 | AH6: 1466 | AI6: 7.75 | AJ6: 119447.45 | AK6: 98.33 | AL6: 43859 | AM6: 45686 | AN6: 60 | AO6: 2500 | AP6: 150000 | AQ6: 45930 | AR6: 102507 | AS6: 102509 | AT6: 2 | AU6: 102473 | AV6: 1529 | AW6: 3813.34 | AX6: 1730.7 | AY6: 106.88 | AZ6: 581.1 | BA6: 533.83 | BB6: 6765.85 | BC6: 1014.88 | BD6: 7780.73 | BE6: 45748 | BF6: 45838 | BG6: 102507 | BH6: 102509 | BI6: 2 | BJ6: 7500 | BK6: -7498 | BL6: 0.79 | BM6: 1.19 | BN6: 0 | BO6: 0 | BP6: 0 | BQ6: -776.04 | BR6: 0 | BS6: 62374.91 | BT6: 0 | BU6: 0 | BV6: 0 | BW6: 0 | BX6: 0 | BY6: 0 | BZ6: 0 | CA6: 0 | CB6: 0 | CC6: 0 | CD6: 0 | CE6: 62374.91 | CF6: 9356.24 | CG6: 71731.15 | CH6: 73562.22 | CI6: 9595.08 | CJ6: 63967.14 | CK6: 31983.57 | CL6: 290 | CM6: 0 | CN6: 0 | CO6: 100 | CQ6: 0 | CR6: 0 | CS6: 0 | CT6: -65027 | CU6: 45626 | CV6: 45626 | CW6: 150036 | CX6: Active | CY6: Name 1 | CZ6: 45817.29 | DA6: 30093.64 | DB6: -70753.15 | DC6: 0.69 | DD6: -5173.62 | DE6: -5949.66
A7: Company B | B7: 43831 | C7: Business Unit 3 | D7: Division 3 | E7: Cost Centre 3 | F7: PARKTOWN | G7: GAUTENG | H7: Manager 3 | I7: 43836 | J7: 43840 | K7: =J7-I7 -> 4 | L7: 1 | M7: =K7-L7 -> 3 | N7: 43850 | O7: 43884 | P7: =O7-N7 -> 34 | Q7: 90 | R7: =P7-Q7 -> -56 | S7: Reg 6 | T7: Contract 6 | U7: Long Term | V7: ONE TON LDV SINGLE CAB | W7: ISUZU | X7: KB 250 D-TEQ FLEETSIDE (SAFETY) | Y7: 2019 | Z7: DIESEL | AA7: 2498 | AB7: 12 | AC7: 4 | AD7: 279652.17 | AE7: 52153.09 | AF7: 0.19 | AG7: 18227.7 | AH7: 1466 | AI7: 7.75 | AL7: 43884 | AM7: 45711 | AN7: 60 | AO7: 2500 | AP7: 118430 | AQ7: 45930 | AR7: 116462 | AS7: 118471 | AT7: 2009 | AU7: 118430 | AV7: 1794 | AW7: 3787.04 | AX7: 1730.7 | AY7: 80.85 | AZ7: 581.1 | BA7: 533.83 | BB7: 6713.52 | BC7: 1007.03 | BD7: 7720.55 | BE7: 45748 | BF7: 45832 | BG7: 114026 | BH7: 118471 | BI7: 4445 | BJ7: 7500 | BK7: -3055 | BL7: 0.79 | BM7: 1.19 | BN7: 0 | BO7: 0 | BP7: 0 | BQ7: -316.19 | BR7: 0 | BS7: 0 | BT7: 0 | BU7: 0 | BV7: 0 | BW7: 0 | BX7: 0 | BY7: 3119.06 | BZ7: 0 | CA7: 0 | CB7: 0 | CC7: 0 | CD7: 0 | CE7: 0 | CF7: 0 | CG7: 0 | CH7: 5296.41 | CI7: 690.84 | CJ7: 4605.57 | CK7: 2.29 | CL7: 0 | CM7: 0 | CN7: 0 | CO7: 97.3822 | CQ7: 0 | CR7: 0 | CS7: 0 | CT7: -49070 | CU7: 45832 | CV7: 45832 | CW7: 118471 | CX7: Active | CY7: Name 1 | CZ7: 33788.01 | DA7: 22170.36 | DB7: -53697.44 | DC7: 0.69 | DD7: -2107.95 | DE7: -2424.14
A8: Company B | B8: 43831 | C8: Business Unit 1 | D8: Division 1 | E8: Cost Centre 1 | F8: MILL SITE | G8: GAUTENG | H8: Manager 1 | I8: 43837 | J8: 43838 | K8: =J8-I8 -> 1 | L8: 1 | M8: =K8-L8 -> 0 | N8: 43851 | O8: 43861 | P8: =O8-N8 -> 10 | Q8: 90 | R8: =P8-Q8 -> -80 | S8: Reg 7 | T8: Contract 7 | U8: Long Term | V8: ONE TON LDV SINGLE CAB | W8: ISUZU | X8: KB 250 D-TEQ FLEETSIDE (SAFETY) | Y8: 2019 | Z8: DIESEL | AA8: 2498 | AB8: 12 | AC8: 12 | AD8: 279652.17 | AE8: 52153.08 | AF8: 0.19 | AG8: 19142.44 | AH8: 1466 | AI8: 7.75 | AJ8: 123525.53 | AK8: 98.43 | AL8: 43861 | AM8: 45688 | AN8: 60 | AO8: 2500 | AP8: 150000 | AQ8: 45961 | AR8: 148313 | AS8: 149193 | AT8: 880 | AU8: 149059 | AV8: 2293 | AW8: 3873.49 | AX8: 1730.7 | AY8: 80.85 | AZ8: 581.1 | BA8: 533.83 | BB8: 6799.97 | BC8: 1020 | BD8: 7819.97 | BE8: 45748 | BF8: 45838 | BG8: 143988 | BH8: 149193 | BI8: 5205 | BJ8: 7500 | BK8: -2295 | BL8: 0.79 | BM8: 1.19 | BN8: 0 | BO8: 0 | BP8: 0 | BQ8: -237.53 | BR8: 0 | BS8: 0 | BT8: 0 | BU8: 0 | BV8: 0 | BW8: 0 | BX8: 0 | BY8: 3070.33 | BZ8: 0 | CA8: 0 | CB8: 0 | CC8: 0 | CD8: 0 | CE8: 0 | CF8: 0 | CG8: 0 | CH8: 5998.89 | CI8: 782.47 | CJ8: 5216.42 | CK8: 5.93 | CL8: 0 | CM8: 0 | CN8: 0 | CO8: 55.9354 | CQ8: 0 | CR8: 0 | CS8: 0 | CT8: -13441 | CU8: 45688 | CV8: 45688 | CW8: 150134 | CX8: Active | CY8: Name 1 | CZ8: 19430.14 | DA8: 12747.4 | DB8: -19608.77 | DC8: 0.69 | DD8: -1583.55 | DE8: -1821.08
A9: Company C | B9: 43831 | C9: Business Unit 2 | D9: Division 2 | E9: Cost Centre 2 | F9: MILL SITE | G9: GAUTENG | H9: Manager 2 | I9: 43838 | J9: 43850 | K9: =J9-I9 -> 12 | L9: 1 | M9: =K9-L9 -> 11 | N9: 43852 | O9: 43862 | P9: =O9-N9 -> 10 | Q9: 90 | R9: =P9-Q9 -> -80 | S9: Reg 8 | T9: Contract 8 | U9: Long Term | V9: ONE TON LDV SINGLE CAB | W9: ISUZU | X9: KB 250 D-TEQ FLEETSIDE (SAFETY) | Y9: 2019 | Z9: DIESEL | AA9: 2498 | AB9: 12 | AC9: 8 | AD9: 279652.17 | AE9: 52153.08 | AF9: 0.19 | AG9: 35043.05 | AH9: 1182 | AI9: 7.75 | AJ9: 120718.17 | AK9: 98.95 | AL9: 43862 | AM9: 45689 | AN9: 60 | AO9: 3000 | AP9: 127709 | AQ9: 45961 | AR9: 125911 | AS9: 127816 | AT9: 1905 | AU9: 127683 | AV9: 1995 | AW9: 3276.21 | AX9: 2077 | AY9: 80.85 | AZ9: 581.1 | BA9: 533.83 | BB9: 6548.99 | BC9: 982.35 | BD9: 7531.34 | BE9: 45748 | BF9: 45838 | BG9: 123673 | BH9: 127816 | BI9: 4143 | BJ9: 9000 | BK9: -4857 | BL9: 0.79 | BM9: 1.19 | BN9: 0 | BO9: 0 | BP9: 0 | BQ9: -633.84 | BR9: 0 | BS9: 0 | BT9: 0 | BU9: 0 | BV9: 0 | BW9: 0 | BX9: 0 | BY9: 2972.87 | BZ9: 0 | CA9: 0 | CB9: 0 | CC9: 0 | CD9: 0 | CE9: 0 | CF9: 0 | CG9: 0 | CH9: 2671.91 | CI9: 348.51 | CJ9: 2323.4 | CK9: 1.22 | CL9: 0 | CM9: 0 | CN9: 0 | CO9: 99.4799 | CQ9: 0 | CR9: 0 | CS9: 0 | CT9: -64317 | CU9: 45808 | CV9: 45808 | CW9: 127842 | CX9: Active | CY9: Name 1 | CZ9: 8200.23 | DA9: 5379.03 | DB9: -45460.72 | DC9: 0.87 | DD9: -4225.59 | DE9: -4859.43
A10: Company C | B10: 43831 | C10: Business Unit 3 | D10: Division 3 | E10: Cost Centre 3 | F10: ERMELO | G10: MPUMALANGA | H10: Manager 3 | I10: 43839 | J10: 43840 | K10: =J10-I10 -> 1 | L10: 1 | M10: =K10-L10 -> 0 | N10: 43853 | O10: 43863 | P10: =O10-N10 -> 10 | Q10: 90 | R10: =P10-Q10 -> -80 | S10: Reg 9 | T10: Contract 9 | U10: Long Term | V10: ONE TON LDV SINGLE CAB | W10: ISUZU | X10: D-MAX 250 HO FLEETSIDE (SAFETY) | Y10: 2020 | Z10: DIESEL | AA10: 2498 | AB10: 12 | AC10: 12 | AD10: 291043.48 | AE10: 56709.18 | AF10: 0.19 | AG10: 18032.91 | AH10: 1436 | AI10: 7.75 | AL10: 43863 | AM10: 45690 | AN10: 60 | AO10: 3000 | AP10: 147009 | AQ10: 46081 | AR10: 145157 | AS10: 147233 | AT10: 2076 | AU10: 147009 | AV10: 2450 | AW10: 3728.95 | AX10: 2076.81 | AY10: 89.1 | AZ10: 581.1 | BA10: 533.83 | BB10: 7009.79 | BC10: 1051.47 | BD10: 8061.26 | BE10: 45748 | BF10: 45825 | BG10: 144169 | BH10: 147233 | BI10: 3064 | BJ10: 9000 | BK10: -5936 | BL10: 0.79 | BM10: 1.19 | BN10: 0 | BO10: 0 | BP10: 0 | BQ10: -614.38 | BR10: 0 | BS10: 0 | BT10: 0 | BU10: 0 | BV10: 0 | BW10: 0 | BX10: 0 | BY10: 4201.63 | BZ10: 0 | CA10: 0 | CB10: 0 | CC10: 0 | CD10: 0 | CE10: 0 | CF10: 0 | CG10: 0 | CH10: 3351.04 | CI10: 437.09 | CJ10: 2913.95 | CK10: 1.4 | CL10: 0 | CM10: 0 | CN10: 0 | CO10: 96.6766 | CQ10: 0 | CR10: 0 | CS10: 0 | CT10: -35991 | CU10: 45825 | CV10: 45825 | CW10: 147233 | CX10: Active | CY10: Name 1 | CZ10: 10822.96 | DA10: 4564.77 | DB10: -31910.81 | DC10: 0.69 | DD10: -4095.84 | DE10: -4710.22
A11: Company C | B11: 43831 | C11: Business Unit 1 | D11: Division 1 | E11: Cost Centre 1 | F11: KAALFONTEIN | G11: GAUTENG | H11: Manager 1 | I11: 43840 | J11: 43841 | K11: =J11-I11 -> 1 | L11: 1 | M11: =K11-L11 -> 0 | N11: 43854 | O11: 43864 | P11: =O11-N11 -> 10 | Q11: 90 | R11: =P11-Q11 -> -80 | S11: Reg 10 | T11: Contract 10 | U11: Long Term | V11: ONE TON LDV DOUBLE CAB | W11: ISUZU | X11: D-MAX 250 HO HI-RIDER D/CAB | Y11: 2020 | Z11: DIESEL | AA11: 2498 | AB11: 12 | AC11: 3 | AD11: 363391.3 | AE11: 72543.26 | AF11: 0.2 | AG11: 8915.66 | AH11: 1718 | AI11: 7.75 | AJ11: 170794 | AK11: 68.23 | AL11: 43864 | AM11: 45691 | AN11: 60 | AO11: 1500 | AP11: 67137 | AQ11: 46203 | AR11: 30090 | AS11: 30478 | AT11: 388 | AU11: 30448 | AV11: 507 | AW11: 4221.91 | AX11: 1170.45 | AY11: 102.85 | AZ11: 581.1 | BA11: 922.77 | BB11: 6999.08 | BC11: 1049.86 | BD11: 8048.94 | BE11: 45748 | BF11: 45838 | BG11: 29023 | BH11: 30478 | BI11: 1455 | BJ11: 4500 | BK11: -3045 | BL11: 0.89 | BM11: 1.36 | BN11: 0 | BO11: 0 | BP11: 0 | BQ11: -356.27 | BR11: 0 | BS11: 0 | BT11: 0 | BU11: 0 | BV11: 0 | BW11: 0 | BX11: 0 | BY11: 1205.49 | BZ11: 0 | CA11: 0 | CB11: 0 | CC11: 0 | CD11: 0 | CE11: 0 | CF11: 0 | CG11: 0 | CH11: 5317.57 | CI11: 693.59 | CJ11: 4623.98 | CK11: 11.92 | CL11: 0 | CM11: 0 | CN11: 0 | CO11: 97.1315 | CQ11: 0 | CR11: 0 | CS11: 0 | CT11: -92552 | CU11: 45838 | CV11: 45838 | CW11: 67167 | CX11: Active | CY11: Name 1 | CZ11: 0 | DA11: 0 | DB11: -64259.47 | DC11: 0.78 | DD11: -2375.1 | DE11: -2731.37
A12: Company C | B12: 43831 | C12: Business Unit 2 | D12: Division 2 | E12: Cost Centre 2 | F12: ELANDSFONTEIN | G12: GAUTENG | H12: Manager 2 | I12: 43841 | J12: 43842 | K12: =J12-I12 -> 1 | L12: 1 | M12: =K12-L12 -> 0 | N12: 43855 | O12: 43986 | P12: =O12-N12 -> 131 | Q12: 90 | R12: =P12-Q12 -> 41 | S12: Reg 11 | T12: Contract 11 | U12: Long Term | V12: ONE TON LDV DOUBLE CAB | W12: ISUZU | X12: D-MAX 250 HO HI-RIDER D/CAB | Y12: 2023 | Z12: DIESEL | AA12: 2498 | AB12: 16 | AC12: 0 | AD12: 440782.61 | AE12: 71421.44 | AF12: 0.16 | AG12: 11953.33 | AH12: 3046 | AI12: 7.75 | AJ12: 185129 | AK12: 42 | AL12: 43986 | AM12: 45812 | AN12: 60 | AO12: 3000 | AP12: 180000 | AQ12: 45991 | AR12: 34652 | AS12: 37767 | AT12: 3115 | AU12: 37154 | AV12: 2064 | AW12: 6035.98 | AX12: 1320 | AY12: 125 | AZ12: 290.99 | BA12: 1083.24 | BB12: 8855.21 | BC12: 1328.28 | BD12: 10183.49 | BE12: 45748 | BF12: 45838 | BG12: 32699 | BH12: 37767 | BI12: 5068 | BJ12: 9000 | BK12: -3932 | BL12: 0.51 | BM12: 1.42 | BN12: 0 | BO12: 0 | BP12: 0 | BQ12: -259.51 | BR12: 0 | BS12: 0 | BT12: 0 | BU12: 0 | BV12: 0 | BW12: 0 | BX12: 0 | BY12: 4062.22 | BZ12: 0 | CA12: 0 | CB12: 0 | CC12: 0 | CD12: 0 | CE12: 0 | CF12: 0 | CG12: 0 | CH12: 8193.9 | CI12: 1068.77 | CJ12: 7125.13 | CK12: 2.29 | CL12: 0 | CM12: 0 | CN12: 0 | CO12: 100 | CQ12: 0 | CR12: 0 | CS12: 0 | CT12: -19410 | CU12: 47118 | CV12: 47118 | CW12: 180613 | CX12: Active | CY12: Name 1 | CZ12: 330.99 | DA12: 921.58 | DB12: -8719.04 | DC12: 0.44 | DD12: -1730.08 | DE12: -1989.59
A13: Company C | B13: 43831 | C13: Business Unit 3 | D13: Division 3 | E13: Cost Centre 3 | F13: RICHARDS BAY | G13: KWAZULU NATAL | H13: Manager 3 | I13: 43842 | J13: 43843 | K13: =J13-I13 -> 1 | L13: 1 | M13: =K13-L13 -> 0 | N13: 43856 | O13: 43866 | P13: =O13-N13 -> 10 | Q13: 90 | R13: =P13-Q13 -> -80 | S13: Reg 12 | T13: Contract 12 | U13: Long Term | V13: ONE TON LDV DOUBLE CAB | W13: ISUZU | X13: D-MAX 250 HO HI-RIDER D/CAB | Y13: 2023 | Z13: DIESEL | AA13: 2498 | AB13: 16 | AC13: 0 | AD13: 460956.52 | AE13: 91595.35 | AF13: 0.2 | AG13: 56494.37 | AH13: 2242.5 | AI13: 7.75 | AJ13: 193602 | AK13: 42 | AL13: 43866 | AM13: 45693 | AN13: 60 | AO13: 1500 | AP13: 90000 | AQ13: 45991 | AR13: 27414 | AS13: 29399 | AT13: 1985 | AU13: 28740 | AV13: 1597 | AW13: 6834.46 | AX13: 570 | AY13: 125 | AZ13: 290.99 | BA13: 1453.23 | BB13: 9273.68 | BC13: 1391.05 | BD13: 10664.73 | BE13: 45748 | BF13: 45838 | BG13: 24289 | BH13: 29399 | BI13: 5110 | BJ13: 4500 | BK13: 610 | BL13: 0.44 | BM13: 2.97 | BN13: 268.4 | BO13: 1811.7 | BP13: 2080.1 | BQ13: 312.02 | BR13: 2392.12 | BS13: 0 | BT13: 0 | BU13: 0 | BV13: 0 | BW13: 0 | BX13: 0 | BY13: 5151.89 | BZ13: 0 | CA13: 0 | CB13: 0 | CC13: 0 | CD13: 0 | CE13: 0 | CF13: 0 | CG13: 0 | CH13: 13056.85 | CI13: 1703.07 | CJ13: 11353.78 | CK13: 5.72 | CL13: 0 | CM13: 0 | CN13: 0 | CO13: 100 | CQ13: 0 | CR13: 0 | CS13: 0 | CT13: 804 | CU13: 47118 | CV13: 47118 | CW13: 90659 | CX13: Active | CY13: Name 1 | CZ13: 1118.04 | DA13: 7546.77 | DB13: -628.14 | DC13: 0.38 | DD13: 0 | DE13: 0
A14: Company D | B14: 43831 | C14: Business Unit 1 | D14: Division 1 | E14: Cost Centre 1 | F14: DURBAN | G14: KWAZULU NATAL | H14: Manager 1 | I14: 43843 | J14: 43846 | K14: =J14-I14 -> 3 | L14: 1 | M14: =K14-L14 -> 2 | N14: 43857 | O14: 43867 | P14: =O14-N14 -> 10 | Q14: 90 | R14: =P14-Q14 -> -80 | S14: Reg 13 | T14: Contract 13 | U14: Long Term | V14: ONE TON LDV DOUBLE CAB | W14: ISUZU | X14: D-MAX 250 HO HI-RIDER D/CAB | Y14: 2023 | Z14: DIESEL | AA14: 2498 | AB14: 16 | AC14: 0 | AD14: 460956.52 | AE14: 91595.35 | AF14: 0.2 | AG14: 25730.64 | AH14: 2431.5 | AI14: 7.75 | AJ14: 193602 | AK14: 42 | AL14: 43867 | AM14: 45694 | AN14: 60 | AO14: 3000 | AP14: 180000 | AQ14: 45991 | AR14: 31771 | AS14: 32013 | AT14: 242 | AU14: 31413 | AV14: 1745 | AW14: 6195.35 | AX14: 1140 | AY14: 125 | AZ14: 290.99 | BA14: 1033.63 | BB14: 8784.97 | BC14: 1317.75 | BD14: 10102.72 | BE14: 45748 | BF14: 45838 | BG14: 30054 | BH14: 32013 | BI14: 1959 | BJ14: 9000 | BK14: -7041 | BL14: 0.44 | BM14: 1.49 | BN14: 0 | BO14: 0 | BP14: 0 | BQ14: -401.34 | BR14: 0 | BS14: 0 | BT14: 0 | BU14: 0 | BV14: 0 | BW14: 0 | BX14: 0 | BY14: 1451.11 | BZ14: 0 | CA14: 0 | CB14: 0 | CC14: 0 | CD14: 0 | CE14: 0 | CF14: 0 | CG14: 0 | CH14: 7025.8 | CI14: 916.41 | CJ14: 6109.39 | CK14: 25.25 | CL14: 0 | CM14: 0 | CN14: 0 | CO14: 100 | CQ14: 0 | CR14: 0 | CS14: 0 | CT14: -24460 | CU14: 47118 | CV14: 47118 | CW14: 180600 | CX14: Active | CY14: Name 1 | CZ14: 0 | DA14: 0 | DB14: -9136.72 | DC14: 0.38 | DD14: -2675.58 | DE14: -3076.92
A15: Company D | B15: 43831 | C15: Business Unit 2 | D15: Division 2 | E15: Cost Centre 2 | F15: VRYHEID | G15: KWAZULU NATAL | H15: Manager 2 | I15: 43844 | J15: 43845 | K15: =J15-I15 -> 1 | L15: 1 | M15: =K15-L15 -> 0 | N15: 43858 | O15: 43868 | P15: =O15-N15 -> 10 | Q15: 90 | R15: =P15-Q15 -> -80 | S15: Reg 14 | T15: Contract 14 | U15: Long Term | V15: ONE TON LDV DOUBLE CAB | W15: FORD | X15: RANGER 2.0 SiT D CAB BASE 4X4 | Y15: 2024 | Z15: DIESEL | AA15: 1998 | AB15: 16 | AC15: 10 | AD15: 482952 | AE15: 29511.33 | AF15: 0.06 | AG15: 24585.1 | AH15: 2617.5 | AI15: 7.75 | AJ15: 224491.8 | AK15: 57.39 | AL15: 43868 | AM15: 45695 | AN15: 60 | AO15: 2000 | AP15: 155396 | AQ15: 46022 | AR15: 73938 | AS15: 77624 | AT15: 3686 | AU15: 77020 | AV15: 4531 | AW15: 6992.54 | AX15: 1200 | AY15: 125 | AZ15: 290.99 | BA15: 1453.23 | BB15: 10061.76 | BC15: 1509.26 | BD15: 11571.02 | BE15: 45748 | BF15: 45838 | BG15: 65352 | BH15: 77624 | BI15: 12272 | BJ15: 6000 | BK15: 6272 | BL15: 0.66 | BM15: 1.49 | BN15: 4139.52 | BO15: 9345.28 | BP15: 13484.8 | BQ15: 2022.72 | BR15: 15507.52 | BS15: 0 | BT15: 0 | BU15: 0 | BV15: 0 | BW15: 0 | BX15: 0 | BY15: 10951.15 | BZ15: 0 | CA15: 0 | CB15: 0 | CC15: 0 | CD15: 0 | CE15: 0 | CF15: 0 | CG15: 0 | CH15: 27078.54 | CI15: 3531.98 | CJ15: 23546.56 | CK15: 6.39 | CL15: 0 | CM15: 0 | CN15: 0 | CO15: 100 | CQ15: 0 | CR15: 0 | CS15: 0 | CT15: 28048 | CU15: 47149 | CV15: 47149 | CW15: 156000 | CX15: Active | CY15: Name 1 | CZ15: 18749.94 | DA15: 38635.05 | DB15: 0 | DC15: 0.6 | DD15: 0 | DE15: 0
A16: Company D | B16: 43831 | C16: Business Unit 3 | D16: Division 3 | E16: Cost Centre 3 | F16: RICHARDS BAY | G16: KWAZULU NATAL | H16: Manager 3 | I16: 43845 | J16: 43846 | K16: =J16-I16 -> 1 | L16: 1 | M16: =K16-L16 -> 0 | N16: 43859 | O16: 43869 | P16: =O16-N16 -> 10 | Q16: 90 | R16: =P16-Q16 -> -80 | S16: Reg 15 | T16: Contract 15 | U16: Long Term | V16: ONE TON LDV DOUBLE CAB | W16: FORD | X16: RANGER 2.0 SiT D CAB BASE 4X4 | Y16: 2024 | Z16: DIESEL | AA16: 1998 | AB16: 16 | AC16: 6 | AD16: 482952 | AE16: 29511.33 | AF16: 0.06 | AG16: 24481.01 | AH16: 2617.5 | AI16: 7.75 | AJ16: 231766.6 | AK16: 58.17 | AL16: 43869 | AM16: 45696 | AN16: 60 | AO16: 1500 | AP16: 126813 | AQ16: 46022 | AR16: 64405 | AS16: 73858 | AT16: 9453 | AU16: 73261 | AV16: 4309 | AW16: 7237.43 | AX16: 855 | AY16: 125 | AZ16: 290.99 | BA16: 1453.23 | BB16: 9961.65 | BC16: 1494.25 | BD16: 11455.9 | BE16: 45748 | BF16: 45838 | BG16: 60754 | BH16: 73858 | BI16: 13104 | BJ16: 4500 | BK16: 8604 | BL16: 0.66 | BM16: 1.83 | BN16: 5678.64 | BO16: 15745.32 | BP16: 21423.96 | BQ16: 3213.59 | BR16: 24637.55 | BS16: 0 | BT16: 0 | BU16: 0 | BV16: 0 | BW16: 0 | BX16: 0 | BY16: 12413.3 | BZ16: 0 | CA16: 0 | CB16: 0 | CC16: 0 | CD16: 0 | CE16: 0 | CF16: 0 | CG16: 0 | CH16: 36093.45 | CI16: 4707.84 | CJ16: 31385.61 | CK16: 3.32 | CL16: 0 | CM16: 0 | CN16: 0 | CO16: 100 | CQ16: 0 | CR16: 0 | CS16: 0 | CT16: 26289 | CU16: 47149 | CV16: 47149 | CW16: 127410 | CX16: Active | CY16: Name 1 | CZ16: 17146.8 | DA16: 40367.73 | DB16: 0 | DC16: 0.57 | DD16: 0 | DE16: 0
A17: Company D | B17: 43831 | C17: Business Unit 1 | D17: Division 1 | E17: Cost Centre 1 | F17: RICHARDS BAY | G17: MPUMALANGA | H17: Manager 1 | I17: 43846 | J17: 43847 | K17: =J17-I17 -> 1 | L17: 1 | M17: =K17-L17 -> 0 | N17: 43860 | O17: 44113 | P17: =O17-N17 -> 253 | Q17: 90 | R17: =P17-Q17 -> 163 | S17: Reg 16 | T17: Contract 16 | U17: Long Term | V17: ONE TON LDV DOUBLE CAB | W17: FORD | X17: RANGER 2.0 SiT D CAB BASE 4X4 | Y17: 2024 | Z17: DIESEL | AA17: 1998 | AB17: 16 | AC17: 4 | AD17: 482952 | AE17: 29511.33 | AF17: 0.06 | AG17: 24598.81 | AH17: 2617.5 | AI17: 7.75 | AJ17: 249769 | AK17: 51.72 | AL17: 44113 | AM17: 45939 | AN17: 60 | AO17: 3000 | AP17: 180000 | AQ17: 46022 | AR17: 45843 | AS17: 47715 | AT17: 1872 | AU17: 47116 | AV17: 2772 | AW17: 7152.61 | AX17: 1710 | AY17: 125 | AZ17: 290.99 | BA17: 1453.23 | BB17: 10731.83 | BC17: 1609.77 | BD17: 12341.6 | BE17: 45748 | BF17: 45838 | BG17: 38748 | BH17: 47715 | BI17: 8967 | BJ17: 9000 | BK17: -33 | BL17: 0.66 | BM17: 1.3 | BN17: 0 | BO17: 0 | BP17: 0 | BQ17: 0 | BR17: 0 | BS17: 0 | BT17: 0 | BU17: 0 | BV17: 0 | BW17: 0 | BX17: 0 | BY17: 5861.52 | BZ17: 0 | CA17: 0 | CB17: 0 | CC17: 0 | CD17: 0 | CE17: 0 | CF17: 0 | CG17: 0 | CH17: 12341.6 | CI17: 1609.77 | CJ17: 10731.83 | CK17: 5.73 | CL17: 0 | CM17: 0 | CN17: 0 | CO17: 100 | CQ17: 0 | CR17: 0 | CS17: 0 | CT17: -5856 | CU17: 47149 | CV17: 47149 | CW17: 180599 | CX17: Active | CY17: Name 1 | CZ17: 0 | DA17: 0 | DB17: -3059.76 | DC17: 0.57 | DD17: 0 | DE17: 0
A18: Company D | B18: 43831 | C18: Business Unit 2 | D18: Division 2 | E18: Cost Centre 2 | F18: DURBAN | G18: KWAZULU NATAL | H18: Manager 2 | I18: 43847 | J18: 43849 | K18: =J18-I18 -> 2 | L18: 1 | M18: =K18-L18 -> 1 | N18: 43861 | O18: 43871 | P18: =O18-N18 -> 10 | Q18: 90 | R18: =P18-Q18 -> -80 | S18: Reg 17 | T18: Contract 17 | U18: Long Term | V18: SEDAN | W18: NISSAN | X18: ALMERA 1.5 ACENTA | Y18: 2020 | Z18: PETROL | AA18: 1498 | AB18: 16 | AC18: 16 | AD18: 220869.57 | AE18: 45823.1 | AF18: 0.21 | AG18: 10524.58 | AH18: 1895 | AI18: 7.75 | AJ18: 92765 | AK18: 42 | AL18: 43871 | AM18: 45698 | AN18: 60 | AO18: 2500 | AP18: 150000 | AQ18: 46022 | AR18: 86625 | AS18: 87826 | AT18: 1201 | AU18: 87181 | AV18: 1585 | AW18: 3169.29 | AX18: 857.6 | AY18: 115 | AZ18: 291 | BA18: 1106.3 | BB18: 5539.19 | BC18: 830.88 | BD18: 6370.07 | BE18: 45748 | BF18: 45838 | BG18: 83188 | BH18: 87826 | BI18: 4638 | BJ18: 7500 | BK18: -2862 | BL18: 0.38 | BM18: 1.01 | BN18: 0 | BO18: 0 | BP18: 0 | BQ18: -145.96 | BR18: 0 | BS18: 0 | BT18: 8446.88 | BU18: 0 | BV18: 0 | BW18: 0 | BX18: 0 | BY18: 0 | BZ18: 0 | CA18: 0 | CB18: 0 | CC18: 0 | CD18: 0 | CE18: 8446.88 | CF18: 1267.03 | CG18: 9713.91 | CH18: 14964.94 | CI18: 1951.95 | CJ18: 13012.99 | CK18: 10.84 | CL18: 0 | CM18: 62 | CN18: 0 | CO18: 100 | CQ18: 0 | CR18: 0 | CS18: 0 | CT18: -50319 | CU18: 45991 | CV18: 45991 | CW18: 150645 | CX18: Active | CY18: Name 1 | CZ18: 193.42 | DA18: 514.09 | DB18: -4206.82 | DC18: 0.34 | DD18: -973.08 | DE18: -1119.04
A19: Company D | B19: 43831 | C19: Business Unit 1 | D19: Division 3 | E19: Cost Centre 3 | F19: VRYHEID | G19: KWAZULU NATAL | H19: Manager 3 | I19: 43848 | J19: 43849 | K19: =J19-I19 -> 1 | L19: 1 | M19: =K19-L19 -> 0 | N19: 43831 | O19: 43872 | P19: =O19-N19 -> 41 | Q19: 90 | R19: =P19-Q19 -> -49 | S19: Reg 18 | T19: Contract 18 | U19: Long Term | V19: SEDAN | W19: SUZUKI | X19: DZIRE 1.2I GA | Y19: 2024 | Z19: PETROL | AA19: 1198 | AB19: 16 | AC19: 0 | AD19: 195565.22 | AE19: 15600 | AF19: 0.08 | AG19: 7270.59 | AH19: 1650 | AI19: 7.75 | AJ19: 105902 | AK19: 54.15 | AL19: 43872 | AM19: 45699 | AN19: 60 | AO19: 1500 | AP19: 90000 | AQ19: 46022 | AR19: 19983 | AS19: 21248 | AT19: 1265 | AU19: 20829 | AV19: 1225 | AW19: 3064.49 | AX19: 570 | AY19: 115 | AZ19: 290.98 | BA19: 1066.91 | BB19: 5107.38 | BC19: 766.11 | BD19: 5873.49 | BE19: 45748 | BF19: 45838 | BG19: 17104 | BH19: 21248 | BI19: 4144 | BJ19: 4500 | BK19: -356 | BL19: 0.44 | BM19: 1 | BN19: 0 | BO19: 0 | BP19: 0 | BQ19: -20.29 | BR19: 0 | BS19: 0 | BT19: 0 | BU19: 0 | BV19: 0 | BW19: 0 | BX19: 0 | BY19: 1316.88 | BZ19: 0 | CA19: 0 | CB19: 0 | CC19: 0 | CD19: 0 | CE19: 0 | CF19: 0 | CG19: 0 | CH19: 5717.92 | CI19: 745.82 | CJ19: 4972.1 | CK19: 3.93 | CL19: 0 | CM19: 0 | CN19: 0 | CO19: 100 | CQ19: 0 | CR19: 0 | CS19: 0 | CT19: -4769 | CU19: 47149 | CV19: 47149 | CW19: 90419 | CX19: Active | CY19: Name 1 | CZ19: 0 | DA19: 0 | DB19: -1812.22 | DC19: 0.38 | DD19: -135.28 | DE19: -155.57
A20: Company D | B20: 43831 | C20: Business Unit 2 | D20: Division 1 | E20: Cost Centre 1 | F20: LADYSMITH | G20: KWAZULU NATAL | H20: Manager 1 | I20: 43849 | J20: 43850 | K20: =J20-I20 -> 1 | L20: 1 | M20: =K20-L20 -> 0 | N20: 43832 | O20: 43873 | P20: =O20-N20 -> 41 | Q20: 90 | R20: =P20-Q20 -> -49 | S20: Reg 19 | T20: Contract 19 | U20: Long Term | V20: ONE TON LDV SINGLE CAB | W20: TOYOTA | X20: HILUX 2.4 GD S AC 5MT | Y20: 2024 | Z20: DIESEL | AA20: 2398 | AB20: 16 | AC20: 0 | AD20: 358957 | AE20: 46664.41 | AF20: 0.13 | AG20: 34060.48 | AH20: 2184 | AI20: 7.75 | AJ20: 150762 | AK20: 42 | AL20: 43873 | AM20: 45700 | AN20: 60 | AO20: 3000 | AP20: 180000 | AQ20: 46022 | AR20: 31353 | AS20: 35603 | AT20: 4250 | AU20: 35179 | AV20: 2069 | AW20: 5743.81 | AX20: 1650 | AY20: 125 | AZ20: 290.99 | BA20: 1033.63 | BB20: 8843.43 | BC20: 1326.51 | BD20: 10169.94 | BE20: 45748 | BF20: 45838 | BG20: 28285 | BH20: 35603 | BI20: 7318 | BJ20: 9000 | BK20: -1682 | BL20: 0.63 | BM20: 1.16 | BN20: 0 | BO20: 0 | BP20: 0 | BQ20: -138.77 | BR20: 0 | BS20: 0 | BT20: 0 | BU20: 0 | BV20: 0 | BW20: 0 | BX20: 0 | BY20: 7562.44 | BZ20: 0 | CA20: 0 | CB20: 0 | CC20: 0 | CD20: 0 | CE20: 0 | CF20: 0 | CG20: 0 | CH20: 9106.07 | CI20: 1187.74 | CJ20: 7918.33 | CK20: 1.86 | CL20: 0 | CM20: 0 | CN20: 0 | CO20: 100 | CQ20: 0 | CR20: 0 | CS20: 0 | CT20: -15919 | CU20: 47149 | CV20: 47149 | CW20: 180424 | CX20: Active | CY20: Name 1 | CZ20: 0 | DA20: 0 | DB20: -8755.45 | DC20: 0.55 | DD20: -925.1 | DE20: -1063.87
A21: Company D | B21: 43831 | C21: Business Unit 3 | D21: Division 2 | E21: Cost Centre 2 | F21: LADYSMITH | G21: KWAZULU NATAL | H21: Manager 2 | I21: 43850 | J21: 43851 | K21: =J21-I21 -> 1 | L21: 1 | M21: =K21-L21 -> 0 | N21: 43833 | O21: 43874 | P21: =O21-N21 -> 41 | Q21: 90 | R21: =P21-Q21 -> -49 | S21: Reg 20 | T21: Contract 20 | U21: Long Term | V21: ONE TON LDV SINGLE CAB | W21: TOYOTA | X21: HILUX 2.4 GD S AC 5MT | Y21: 2024 | Z21: DIESEL | AA21: 2398 | AB21: 16 | AC21: 0 | AD21: 358957 | AE21: 46664.41 | AF21: 0.13 | AG21: 34085.19 | AH21: 2184 | AI21: 7.75 | AJ21: 150762 | AK21: 42 | AL21: 43874 | AM21: 45701 | AN21: 60 | AO21: 3000 | AP21: 180000 | AQ21: 46022 | AR21: 30867 | AS21: 33199 | AT21: 2332 | AU21: 32773 | AV21: 1928 | AW21: 5744.31 | AX21: 1650 | AY21: 125 | AZ21: 290.99 | BA21: 1033.63 | BB21: 8843.93 | BC21: 1326.59 | BD21: 10170.52 | BE21: 45748 | BF21: 45838 | BG21: 28656 | BH21: 33199 | BI21: 4543 | BJ21: 9000 | BK21: -4457 | BL21: 0.63 | BM21: 1.16 | BN21: 0 | BO21: 0 | BP21: 0 | BQ21: -367.7 | BR21: 0 | BS21: 0 | BT21: 0 | BU21: 0 | BV21: 0 | BW21: 0 | BX21: 0 | BY21: 3952.62 | BZ21: 0 | CA21: 0 | CB21: 0 | CC21: 0 | CD21: 0 | CE21: 0 | CF21: 0 | CG21: 0 | CH21: 7351.47 | CI21: 958.89 | CJ21: 6392.58 | CK21: 2.74 | CL21: 0 | CM21: 0 | CN21: 0 | CO21: 100 | CQ21: 0 | CR21: 0 | CS21: 0 | CT21: -18325 | CU21: 47149 | CV21: 47149 | CW21: 180426 | CX21: Active | CY21: Name 1 | CZ21: 0 | DA21: 0 | DB21: -10078.75 | DC21: 0.55 | DD21: -2451.35 | DE21: -2819.05
A22: Company E | B22: 43831 | C22: Business Unit 1 | D22: Division 3 | E22: Cost Centre 3 | F22: PIET RETIEF | G22: MPUMALANGA | H22: Manager 3 | I22: 43851 | J22: 43857 | K22: =J22-I22 -> 6 | L22: 1 | M22: =K22-L22 -> 5 | N22: 43834 | O22: 43875 | P22: =O22-N22 -> 41 | Q22: 90 | R22: =P22-Q22 -> -49 | S22: Reg 21 | T22: Contract 21 | U22: Long Term | V22: MINIBUS | W22: VOLKSWAGEN | X22: T6.1 KOMBI 2.0 TDI TRENDLINE DSG | Y22: 2024 | Z22: DIESEL | AA22: 1998 | AB22: 16 | AC22: 13 | AD22: 771217.39 | AE22: 44275.33 | AF22: 0.06 | AG22: 8147.3 | AH22: 2124 | AI22: 7.75 | AJ22: 339336 | AK22: 44 | AL22: 43875 | AM22: 45702 | AN22: 60 | AO22: 10000 | AP22: 220000 | AQ22: 46022 | AR22: 80118 | AS22: 85107 | AT22: 4989 | AU22: 84680 | AV22: 4981 | AW22: 21889.88 | AX22: 4500 | AY22: 190 | AZ22: 290.99 | BA22: 1405.42 | BB22: 28276.29 | BC22: 4241.44 | BD22: 32517.73 | BE22: 45748 | BF22: 45838 | BG22: 71704 | BH22: 85107 | BI22: 13403 | BJ22: 30000 | BK22: -16597 | BL22: 0.52 | BM22: 1.96 | BN22: 0 | BO22: 0 | BP22: 0 | BQ22: -1120.3 | BR22: 0 | BS22: 0 | BT22: 0 | BU22: 0 | BV22: 0 | BW22: 0 | BX22: 0 | BY22: 8976.68 | BZ22: 0 | CA22: 0 | CB22: 0 | CC22: 0 | CD22: 0 | CE22: 0 | CF22: 0 | CG22: 0 | CH22: 23928.78 | CI22: 3121.14 | CJ22: 20807.64 | CK22: 4.17 | CL22: 0 | CM22: 0 | CN22: 0 | CO22: 100 | CQ22: 0 | CR22: 0 | CS22: 0 | CT22: -85648 | CU22: 45991 | CV22: 45991 | CW22: 220427 | CX22: Active | CY22: Name 1 | CZ22: 0 | DA22: 0 | DB22: -38541.6 | DC22: 0.45 | DD22: -7468.65 | DE22: -8588.95
... A34: Company B | B34: 43862 | C34: Business Unit 3 | D34: Division 2 | E34: Cost Centre 2 | F34: DURBAN | G34: KWAZULU NATAL | H34: Manager 2 | I34: 43865 | J34: 43866 | K34: =J34-I34 -> 1 | L34: 1 | M34: =K34-L34 -> 0 | N34: 43879 | O34: 43889 | P34: =O34-N34 -> 10 | Q34: 90 | R34: =P34-Q34 -> -80 | S34: Reg 35 | T34: Contract 35 | U34: Long Term | V34: MINIBUS | W34: TOYOTA | X34: QUANTUM 2.5 D-4D 14-SEATER BUS | Y34: 2024 | Z34: DIESEL | AA34: 2498 | AB34: 16 | AC34: 7 | AD34: 628087 | AE34: 75370.44 | AF34: 0.12 | AG34: 24391.27 | AH34: 2621 | AI34: 7.75 | AJ34: 301482 | AK34: 48 | AL34: 43889 | AM34: 45716 | AN34: 60 | AO34: 2500 | AP34: 150000 | AQ34: 46053 | AR34: 28835 | AS34: 32286 | AT34: 3451 | AU34: 31670 | AV34: 2111 | AW34: 8493.29 | AX34: 1575 | AY34: 190 | AZ34: 290.99 | BA34: 1453.23 | BB34: 12002.51 | BC34: 1800.38 | BD34: 13802.89 | BE34: 45748 | BF34: 45838 | BG34: 19889 | BH34: 32286 | BI34: 12397 | BJ34: 7500 | BK34: 4897 | BL34: 0.72 | BM34: 2.18 | BN34: 3525.84 | BO34: 10675.46 | BP34: 14201.3 | BQ34: 2130.2 | BR34: 16331.5 | BS34: 0 | BT34: 0 | BU34: 0 | BV34: 0 | BW34: 0 | BX34: 0 | BY34: 10534.25 | BZ34: 0 | CA34: 0 | CB34: 0 | CC34: 0 | CD34: 0 | CE34: 0 | CF34: 0 | CG34: 0 | CH34: 30134.39 | CI34: 3930.58 | CJ34: 26203.81 | CK34: 7.59 | CL34: 0 | CM34: 0 | CN34: 0 | CO34: 100 | CQ34: 0 | CR34: 0 | CS34: 0 | CT34: -8049 | CU34: 47208 | CV34: 47208 | CW34: 150616 | CX34: Active | CY34: Name 1 | CZ34: 3525.84 | DA34: 10675.46 | DB34: -8155.98 | DC34: 0.63 | DD34: 0 | DE34: 0
A35: Company B | B35: 43862 | C35: Business Unit 1 | D35: Division 1 | E35: Cost Centre 1 | F35: DURBAN | G35: KWAZULU NATAL | H35: Manager 3 | I35: 43866 | J35: 43867 | K35: =J35-I35 -> 1 | L35: 1 | M35: =K35-L35 -> 0 | N35: 43880 | O35: 43890 | P35: =O35-N35 -> 10 | Q35: 90 | R35: =P35-Q35 -> -80 | S35: Reg 36 | T35: Contract 36 | U35: Long Term | V35: MINIBUS | W35: TOYOTA | X35: QUANTUM 2.5 D-4D 14-SEATER BUS | Y35: 2024 | Z35: DIESEL | AA35: 2498 | AB35: 16 | AC35: 2 | AD35: 592067 | AE35: 95248 | AF35: 0.16 | AG35: 24242.28 | AH35: 2715.5 | AI35: 7.75 | AJ35: 284192 | AK35: 58.2 | AL35: 43890 | AM35: 2/29/2025 | AN35: 60 | AO35: 2500 | AP35: 142725 | AQ35: 46081 | AR35: 15238 | AS35: 15360 | AT35: 122 | AU35: 14718 | AV35: 981 | AW35: 7623.68 | AX35: 1626.92 | AY35: 190 | AZ35: 290.99 | BA35: 1438.02 | BB35: 11169.61 | BC35: 1675.44 | BD35: 12845.05 | BE35: 45748 | BF35: 45838 | BG35: 14927 | BH35: 15360 | BI35: 433 | BJ35: 7500 | BK35: -7067 | BL35: 0.72 | BM35: 2.15 | BN35: 0 | BO35: 0 | BP35: 0 | BQ35: -667.83 | BR35: 0 | BS35: 0 | BT35: 0 | BU35: 0 | BV35: 0 | BW35: 0 | BX35: 0 | BY35: 0 | BZ35: 0 | CA35: 0 | CB35: 0 | CC35: 0 | CD35: 0 | CE35: 0 | CF35: 0 | CG35: 0 | CH35: 7725.01 | CI35: 1007.61 | CJ35: 6717.4 | CK35: 55.06 | CL35: 0 | CM35: 0 | CN35: 0 | CO35: 100 | CQ35: 0 | CR35: 0 | CS35: 0 | CT35: -24343 | CU35: 47208 | CV35: 47208 | CW35: 143367 | CX35: Active | CY35: Name 1 | CZ35: 0 | DA35: 0 | DB35: -15477.84 | DC35: 0.63 | DD35: -4452.21 | DE35: -5120.04
A36: Company C | B36: 43862 | C36: Business Unit 2 | D36: Division 2 | E36: Cost Centre 2 | F36: DURBAN | G36: KWAZULU NATAL | H36: Manager 1 | I36: 43867 | J36: 43868 | K36: =J36-I36 -> 1 | L36: 1 | M36: =K36-L36 -> 0 | N36: 43881 | O36: 43891 | P36: =O36-N36 -> 10 | Q36: 90 | R36: =P36-Q36 -> -80 | S36: Reg 37 | T36: Contract 37 | U36: Long Term | V36: MINIBUS | W36: TOYOTA | X36: QUANTUM 2.5 D-4D 14-SEATER BUS | Y36: 2024 | Z36: DIESEL | AA36: 2498 | AB36: 16 | AC36: 0 | AD36: 628087 | AE36: 75370.44 | AF36: 0.12 | AG36: 24528.21 | AH36: 3171 | AI36: 7.75 | AJ36: 301482 | AK36: 48 | AL36: 43891 | AM36: 45717 | AN36: 60 | AO36: 2500 | AP36: 150000 | AQ36: 46081 | AR36: 14667 | AS36: 17658 | AT36: 2991 | AU36: 17032 | AV36: 1135 | AW36: 8314.36 | AX36: 1575 | AY36: 190 | AZ36: 290.99 | BA36: 1453.23 | BB36: 11823.58 | BC36: 1773.54 | BD36: 13597.12 | BE36: 45748 | BF36: 45838 | BG36: 10974 | BH36: 17658 | BI36: 6684 | BJ36: 7500 | BK36: -816 | BL36: 0.72 | BM36: 2.18 | BN36: 0 | BO36: 0 | BP36: 0 | BQ36: -77.11 | BR36: 0 | BS36: 0 | BT36: 0 | BU36: 0 | BV36: 0 | BW36: 0 | BX36: 0 | BY36: 7486.92 | BZ36: 0 | CA36: 0 | CB36: 0 | CC36: 0 | CD36: 0 | CE36: 0 | CF36: 0 | CG36: 0 | CH36: 13005.93 | CI36: 1696.43 | CJ36: 11309.5 | CK36: 3.78 | CL36: 0 | CM36: 0 | CN36: 0 | CO36: 100 | CQ36: 0 | CR36: 0 | CS36: 0 | CT36: -21618 | CU36: 47208 | CV36: 47208 | CW36: 150626 | CX36: Active | CY36: Name 1 | CZ36: 0 | DA36: 0 | DB36: -13619.34 | DC36: 0.63 | DD36: -514.08 | DE36: -591.19
A37: Company C | B37: 43862 | C37: Business Unit 3 | D37: Division 3 | E37: Cost Centre 3 | F37: RICHARDS BAY | G37: KWAZULU NATAL | H37: Manager 2 | I37: 43868 | J37: 43869 | K37: =J37-I37 -> 1 | L37: 1 | M37: =K37-L37 -> 0 | N37: 43882 | O37: 43892 | P37: =O37-N37 -> 10 | Q37: 90 | R37: =P37-Q37 -> -80 | S37: Reg 38 | T37: Contract 38 | U37: Long Term | V37: MINIBUS | W37: HYUNDAI | X37: STARIA 2.2D EXECUTIVE 11 SEATER AT | Y37: 2024 | Z37: DIESEL | AA37: 2198 | AB37: 16 | AC37: 12 | AD37: 782173.91 | AE37: 69395.65 | AF37: 0.09 | AG37: 9991.96 | AH37: 2310 | AI37: 7.75 | AJ37: 302090 | AK37: 38.62 | AL37: 43892 | AM37: 45718 | AN37: 60 | AO37: 4000 | AP37: 220000 | AQ37: 46081 | AR37: 76515 | AS37: 81977 | AT37: 5462 | AU37: 81331 | AV37: 5422 | AW37: 12182.34 | AX37: 2520 | AY37: 190 | AZ37: 291 | BA37: 1522.99 | BB37: 16706.33 | BC37: 2505.95 | BD37: 19212.28 | BE37: 45748 | BF37: 45838 | BG37: 65171 | BH37: 81977 | BI37: 16806 | BJ37: 12000 | BK37: 4806 | BL37: 0.72 | BM37: 2.18 | BN37: 3460.32 | BO37: 10477.08 | BP37: 13937.4 | BQ37: 2090.61 | BR37: 16028.01 | BS37: 0 | BT37: 0 | BU37: 0 | BV37: 0 | BW37: 0 | BX37: 0 | BY37: 12321.1 | BZ37: 0 | CA37: 0 | CB37: 0 | CC37: 0 | CD37: 0 | CE37: 0 | CF37: 0 | CG37: 0 | CH37: 35240.29 | CI37: 4596.56 | CJ37: 30643.73 | CK37: 5.61 | CL37: 0 | CM37: 0 | CN37: 0 | CO37: 100 | CQ37: 0 | CR37: 0 | CS37: 0 | CT37: 19490 | CU37: 47057 | CV37: 47057 | CW37: 220646 | CX37: Active | CY37: Name 1 | CZ37: 17626.32 | DA37: 53368.58 | DB37: -3427.83 | DC37: 0.63 | DD37: 0 | DE37: 0
A38: Company C | B38: 43862 | C38: Business Unit 1 | D38: Division 1 | E38: Cost Centre 1 | F38: DURBAN | G38: KWAZULU NATAL | H38: Manager 3 | I38: 43869 | J38: 43873 | K38: =J38-I38 -> 4 | L38: 1 | M38: =K38-L38 -> 3 | N38: 43883 | O38: 43893 | P38: =O38-N38 -> 10 | Q38: 90 | R38: =P38-Q38 -> -80 | S38: Reg 39 | T38: Contract 39 | U38: Long Term | V38: MINIBUS | W38: TOYOTA | X38: QUANTUM 2.5 D-4D 14-SEATER BUS | Y38: 2024 | Z38: DIESEL | AA38: 2498 | AB38: 16 | AC38: 4 | AD38: 628087 | AE38: 75370.44 | AF38: 0.12 | AG38: 24564.84 | AH38: 3200 | AI38: 7.75 | AJ38: 301482 | AK38: 48 | AL38: 43893 | AM38: 45719 | AN38: 60 | AO38: 2500 | AP38: 150000 | AQ38: 46081 | AR38: 16686 | AS38: 20306 | AT38: 3620 | AU38: 19660 | AV38: 1404 | AW38: 8506.46 | AX38: 1575 | AY38: 190 | AZ38: 290.99 | BA38: 1453.23 | BB38: 12015.68 | BC38: 1802.35 | BD38: 13818.03 | BE38: 45748 | BF38: 45838 | BG38: 14333 | BH38: 20306 | BI38: 5973 | BJ38: 7500 | BK38: -1527 | BL38: 0.72 | BM38: 2.18 | BN38: 0 | BO38: 0 | BP38: 0 | BQ38: -144.3 | BR38: 0 | BS38: 0 | BT38: 0 | BU38: 0 | BV38: 0 | BW38: 0 | BX38: 0 | BY38: 10523.51 | BZ38: 0 | CA38: 0 | CB38: 0 | CC38: 0 | CD38: 0 | CE38: 0 | CF38: 0 | CG38: 0 | CH38: 12711.72 | CI38: 1658.05 | CJ38: 11053.67 | CK38: 3.05 | CL38: 0 | CM38: 0 | CN38: 0 | CO38: 100 | CQ38: 0 | CR38: 0 | CS38: 0 | CT38: -17559 | CU38: 47238 | CV38: 47238 | CW38: 150646 | CX38: Active | CY38: Name 1 | CZ38: 0 | DA38: 0 | DB38: -11062.17 | DC38: 0.63 | DD38: -962.01 | DE38: -1106.31
A39: Company C | B39: 43862 | C39: Business Unit 2 | D39: Division 2 | E39: Cost Centre 2 | F39: DURBAN | G39: KWAZULU NATAL | H39: Manager 1 | I39: 43870 | J39: 43871 | K39: =J39-I39 -> 1 | L39: 1 | M39: =K39-L39 -> 0 | N39: 43884 | O39: 43986 | P39: =O39-N39 -> 102 | Q39: 90 | R39: =P39-Q39 -> 12 | S39: Reg 40 | T39: Contract 40 | U39: Long Term | V39: ONE TON LDV SINGLE CAB | W39: ISUZU | X39: D-MAX 250 HO FLEETSIDE (SAFETY) | Y39: 2024 | Z39: DIESEL | AA39: 2498 | AB39: 16 | AC39: 0 | AD39: 365565.22 | AE39: 71993.18 | AF39: 0.2 | AG39: 31604.48 | AH39: 2297 | AI39: 7.75 | AJ39: 164504 | AK39: 45 | AL39: 43986 | AM39: 45812 | AN39: 60 | AO39: 2000 | AP39: 72000 | AQ39: 46081 | AR39: 20204 | AS39: 25962 | AT39: 5758 | AU39: 25360 | AV39: 1691 | AW39: 6947.39 | AX39: 1600 | AY39: 125 | AZ39: 291 | BA39: 1083.24 | BB39: 10046.63 | BC39: 1506.99 | BD39: 11553.62 | BE39: 45748 | BF39: 45838 | BG39: 12101 | BH39: 25962 | BI39: 13861 | BJ39: 6000 | BK39: 7861 | BL39: 0.92 | BM39: 2.79 | BN39: 7232.12 | BO39: 21932.19 | BP39: 29164.31 | BQ39: 4374.65 | BR39: 33538.96 | BS39: 0 | BT39: 0 | BU39: 0 | BV39: 0 | BW39: 0 | BX39: 0 | BY39: 10008.22 | BZ39: 0 | CA39: 70 | CB39: 0 | CC39: 0 | CD39: 0 | CE39: 0 | CF39: 0 | CG39: 0 | CH39: 45092.58 | CI39: 5881.64 | CJ39: 39210.94 | CK39: 6.81 | CL39: 0 | CM39: 0 | CN39: 0 | CO39: 100 | CQ39: 0 | CR39: 0 | CS39: 0 | CT39: -4968 | CU39: 46477 | CV39: 46477 | CW39: 72602 | CX39: Active | CY39: Name 1 | CZ39: 7232.12 | DA39: 21932.19 | DB39: -10176.8 | DC39: 0.8 | DD39: 0 | DE39: 0
A40: Company C | B40: 43862 | C40: Business Unit 3 | D40: Division 3 | E40: Cost Centre 3 | F40: LADYSMITH | G40: KWAZULU NATAL | H40: Manager 2 | I40: 43871 | J40: 43872 | K40: =J40-I40 -> 1 | L40: 1 | M40: =K40-L40 -> 0 | N40: 43885 | O40: 43895 | P40: =O40-N40 -> 10 | Q40: 90 | R40: =P40-Q40 -> -80 | S40: Reg 41 | T40: Contract 41 | U40: Long Term | V40: ONE TON LDV DOUBLE CAB | W40: FORD | X40: RANGER 2.0 SiT D CAB BASE 4X2 | Y40: 2024 | Z40: DIESEL | AA40: 1998 | AB40: 16 | AC40: 4 | AD40: 444087 | AE40: 25898.69 | AF40: 0.06 | AG40: 35012.31 | AH40: 2519 | AI40: 7.75 | AJ40: 229948 | AK40: 51.78 | AL40: 43895 | AM40: 45721 | AN40: 60 | AO40: 3000 | AP40: 180000 | AQ40: 46081 | AR40: 35369 | AS40: 38544 | AT40: 3175 | AU40: 38156 | AV40: 2725 | AW40: 6934.66 | AX40: 1650 | AY40: 125 | AZ40: 290.99 | BA40: 1453.23 | BB40: 10453.88 | BC40: 1568.08 | BD40: 12021.96 | BE40: 45748 | BF40: 45838 | BG40: 31071 | BH40: 38544 | BI40: 7473 | BJ40: 9000 | BK40: -1527 | BL40: 0.63 | BM40: 1.19 | BN40: 0 | BO40: 0 | BP40: 0 | BQ40: -125.98 | BR40: 0 | BS40: 0 | BT40: 0 | BU40: 0 | BV40: 0 | BW40: 0 | BX40: 0 | BY40: 5874.44 | BZ40: 0 | CA40: 0 | CB40: 0 | CC40: 0 | CD40: 0 | CE40: 0 | CF40: 0 | CG40: 0 | CH40: 11056.13 | CI40: 1442.1 | CJ40: 9614.03 | CK40: 3.03 | CL40: 0 | CM40: 0 | CN40: 0 | CO40: 100 | CQ40: 0 | CR40: 0 | CS40: 0 | CT40: -5717 | CU40: 47238 | CV40: 47238 | CW40: 180388 | CX40: Active | CY40: Name 1 | CZ40: 564.3 | DA40: 0 | DB40: -3700.4 | DC40: 0.55 | DD40: -839.85 | DE40: -965.83
A41: Company D | B41: 43862 | C41: Business Unit 1 | D41: Division 1 | E41: Cost Centre 1 | F41: LADYSMITH | G41: KWAZULU NATAL | H41: Manager 3 | I41: 43872 | J41: 43873 | K41: =J41-I41 -> 1 | L41: 1 | M41: =K41-L41 -> 0 | N41: 43886 | O41: 43896 | P41: =O41-N41 -> 10 | Q41: 90 | R41: =P41-Q41 -> -80 | S41: Reg 42 | T41: Contract 42 | U41: Long Term | V41: ONE TON LDV DOUBLE CAB | W41: FORD | X41: RANGER 2.0 SiT D CAB BASE 4X2 | Y41: 2024 | Z41: DIESEL | AA41: 1998 | AB41: 16 | AC41: 4 | AD41: 444087 | AE41: 25898.69 | AF41: 0.06 | AG41: 52135.71 | AH41: 2519 | AI41: 7.75 | AJ41: 229948 | AK41: 51.78 | AL41: 43896 | AM41: 45722 | AN41: 60 | AO41: 3000 | AP41: 180000 | AQ41: 46081 | AR41: 35290 | AS41: 37650 | AT41: 2360 | AU41: 37262 | AV41: 2662 | AW41: 7737.91 | AX41: 1650 | AY41: 125 | AZ41: 291 | BA41: 1453.23 | BB41: 11257.14 | BC41: 1688.57 | BD41: 12945.71 | BE41: 45748 | BF41: 45838 | BG41: 29159 | BH41: 37650 | BI41: 8491 | BJ41: 9000 | BK41: -509 | BL41: 0.63 | BM41: 1.19 | BN41: 0 | BO41: 0 | BP41: 0 | BQ41: -41.99 | BR41: 0 | BS41: 0 | BT41: 0 | BU41: 0 | BV41: 0 | BW41: 0 | BX41: 0 | BY41: 4265.48 | BZ41: 0 | CA41: 0 | CB41: 0 | CC41: 0 | CD41: 0 | CE41: 0 | CF41: 0 | CG41: 0 | CH41: 12623.77 | CI41: 1646.58 | CJ41: 10977.19 | CK41: 4.65 | CL41: 0 | CM41: 0 | CN41: 0 | CO41: 100 | CQ41: 0 | CR41: 0 | CS41: 0 | CT41: -6020 | CU41: 47238 | CV41: 47238 | CW41: 180388 | CX41: Active | CY41: Name 1 | CZ41: 839.3 | DA41: 0 | DB41: -3700.4 | DC41: 0.55 | DD41: -279.95 | DE41: -321.94
A42: Company D | B42: 43862 | C42: Business Unit 2 | D42: Division 2 | E42: Cost Centre 2 | F42: LADYSMITH | G42: KWAZULU NATAL | H42: Manager 1 | I42: 43873 | J42: 43879 | K42: =J42-I42 -> 6 | L42: 1 | M42: =K42-L42 -> 5 | N42: 43887 | O42: 43897 | P42: =O42-N42 -> 10 | Q42: 90 | R42: =P42-Q42 -> -80 | S42: Reg 43 | T42: Contract 43 | U42: Long Term | V42: ONE TON LDV DOUBLE CAB | W42: FORD | X42: RANGER 2.0 SiT D CAB BASE 4X2 | Y42: 2024 | Z42: DIESEL | AA42: 1998 | AB42: 16 | AC42: 4 | AD42: 444087 | AE42: 25898.69 | AF42: 0.06 | AG42: 35035.12 | AH42: 2519 | AI42: 7.75 | AJ42: 229948 | AK42: 51.78 | AL42: 43897 | AM42: 45723 | AN42: 60 | AO42: 3000 | AP42: 180000 | AQ42: 46081 | AR42: 38476 | AS42: 40433 | AT42: 1957 | AU42: 40045 | AV42: 2860 | AW42: 6892.2 | AX42: 1650 | AY42: 125 | AZ42: 291 | BA42: 1453.23 | BB42: 10411.43 | BC42: 1561.71 | BD42: 11973.14 | BE42: 45748 | BF42: 45838 | BG42: 31520 | BH42: 40433 | BI42: 8913 | BJ42: 9000 | BK42: -87 | BL42: 0.63 | BM42: 1.19 | BN42: 0 | BO42: 0 | BP42: 0 | BQ42: 0 | BR42: 0 | BS42: 0 | BT42: 0 | BU42: 0 | BV42: 0 | BW42: 0 | BX42: 0 | BY42: 3032.25 | BZ42: 0 | CA42: 0 | CB42: 0 | CC42: 0 | CD42: 0 | CE42: 0 | CF42: 0 | CG42: 0 | CH42: 11973.14 | CI42: 1561.71 | CJ42: 10411.43 | CK42: 5.32 | CL42: 0 | CM42: 0 | CN42: 0 | CO42: 100 | CQ42: 0 | CR42: 0 | CS42: 0 | CT42: -3828 | CU42: 47238 | CV42: 47238 | CW42: 180388 | CX42: Active | CY42: Name 1 | CZ42: 0 | DA42: 0 | DB42: -1885.95 | DC42: 0.55 | DD42: 0 | DE42: 0
A43: Company D | B43: 43862 | C43: Business Unit 3 | D43: Division 3 | E43: Cost Centre 3 | F43: LADYSMITH | G43: KWAZULU NATAL | H43: Manager 2 | I43: 43874 | J43: 43875 | K43: =J43-I43 -> 1 | L43: 1 | M43: =K43-L43 -> 0 | N43: 43888 | O43: 43898 | P43: =O43-N43 -> 10 | Q43: 90 | R43: =P43-Q43 -> -80 | S43: Reg 44 | T43: Contract 44 | U43: Long Term | V43: ONE TON LDV DOUBLE CAB | W43: FORD | X43: RANGER 2.0 SiT D CAB BASE 4X2 | Y43: 2024 | Z43: DIESEL | AA43: 1998 | AB43: 16 | AC43: 5 | AD43: 444087 | AE43: 25898.69 | AF43: 0.06 | AG43: 52514.38 | AH43: 2519 | AI43: 7.75 | AJ43: 229948 | AK43: 51.78 | AL43: 43898 | AM43: 45724 | AN43: 60 | AO43: 3000 | AP43: 180000 | AQ43: 46081 | AR43: 36026 | AS43: 38454 | AT43: 2428 | AU43: 38067 | AV43: 2719 | AW43: 7745.58 | AX43: 1650 | AY43: 125 | AZ43: 291 | BA43: 1453.23 | BB43: 11264.81 | BC43: 1689.72 | BD43: 12954.53 | BE43: 45748 | BF43: 45838 | BG43: 29682 | BH43: 38454 | BI43: 8772 | BJ43: 9000 | BK43: -228 | BL43: 0.63 | BM43: 1.19 | BN43: 0 | BO43: 0 | BP43: 0 | BQ43: 0 | BR43: 0 | BS43: 0 | BT43: 0 | BU43: 0 | BV43: 0 | BW43: 0 | BX43: 0 | BY43: 5126.16 | BZ43: 0 | CA43: 0 | CB43: 0 | CC43: 0 | CD43: 0 | CE43: 0 | CF43: 0 | CG43: 0 | CH43: 12954.53 | CI43: 1689.72 | CJ43: 11264.81 | CK43: 4.64 | CL43: 0 | CM43: 0 | CN43: 0 | CO43: 100 | CQ43: 0 | CR43: 0 | CS43: 0 | CT43: -5215 | CU43: 47238 | CV43: 47238 | CW43: 180387 | CX43: Active | CY43: Name 1 | CZ43: 0 | DA43: 0 | DB43: -2742.85 | DC43: 0.55 | DD43: 0 | DE43: 0
A44: Company A | B44: 43862 | C44: Business Unit 1 | D44: Division 1 | E44: Cost Centre 1 | F44: LADYSMITH | G44: KWAZULU NATAL | H44: Manager 3 | I44: 43875 | J44: 43876 | K44: =J44-I44 -> 1 | L44: 1 | M44: =K44-L44 -> 0 | N44: 43889 | O44: 43899 | P44: =O44-N44 -> 10 | Q44: 90 | R44: =P44-Q44 -> -80 | S44: Reg 45 | T44: Contract 45 | U44: Long Term | V44: ONE TON LDV DOUBLE CAB | W44: FORD | X44: RANGER 2.0 SiT D CAB BASE 4X2 | Y44: 2024 | Z44: DIESEL | AA44: 1998 | AB44: 16 | AC44: 4 | AD44: 444087 | AE44: 25898.69 | AF44: 0.06 | AG44: 52573.78 | AH44: 2519 | AI44: 7.75 | AJ44: 229948 | AK44: 51.78 | AL44: 43899 | AM44: 45725 | AN44: 60 | AO44: 3000 | AP44: 180000 | AQ44: 46081 | AR44: 32786 | AS44: 33024 | AT44: 238 | AU44: 32634 | AV44: 2331 | AW44: 7746.77 | AX44: 1650 | AY44: 125 | AZ44: 291 | BA44: 1453.23 | BB44: 11266 | BC44: 1689.9 | BD44: 12955.9 | BE44: 45748 | BF44: 45838 | BG44: 25267 | BH44: 33024 | BI44: 7757 | BJ44: 9000 | BK44: -1243 | BL44: 0.63 | BM44: 1.19 | BN44: 0 | BO44: 0 | BP44: 0 | BQ44: -102.55 | BR44: 0 | BS44: 0 | BT44: 0 | BU44: 0 | BV44: 0 | BW44: 0 | BX44: 0 | BY44: 0 | BZ44: 0 | CA44: 0 | CB44: 0 | CC44: 0 | CD44: 0 | CE44: 0 | CF44: 0 | CG44: 0 | CH44: 12169.7 | CI44: 1587.35 | CJ44: 10582.35 | CK44: 44.46 | CL44: 0 | CM44: 0 | CN44: 0 | CO44: 100 | CQ44: 0 | CR44: 0 | CS44: 0 | CT44: -10648 | CU44: 47238 | CV44: 47238 | CW44: 180390 | CX44: Active | CY44: Name 1 | CZ44: 0 | DA44: 0 | DB44: -5847.05 | DC44: 0.55 | DD44: -683.65 | DE44: -786.2
A45: Company D | B45: 43862 | C45: Business Unit 2 | D45: Division 2 | E45: Cost Centre 2 | F45: LADYSMITH | G45: KWAZULU NATAL | H45: Manager 1 | I45: 43876 | J45: 43877 | K45: =J45-I45 -> 1 | L45: 1 | M45: =K45-L45 -> 0 | N45: 43889 | O45: 43900 | P45: =O45-N45 -> 11 | Q45: 90 | R45: =P45-Q45 -> -79 | S45: Reg 46 | T45: Contract 46 | U45: Long Term | V45: ONE TON LDV DOUBLE CAB | W45: FORD | X45: RANGER 2.0 SiT D CAB BASE 4X2 | Y45: 2024 | Z45: DIESEL | AA45: 1998 | AB45: 16 | AC45: 4 | AD45: 444087 | AE45: 25898.69 | AF45: 0.06 | AG45: 52544.92 | AH45: 2519 | AI45: 7.75 | AJ45: 229948 | AK45: 51.78 | AL45: 43900 | AM45: 45726 | AN45: 60 | AO45: 3000 | AP45: 180000 | AQ45: 46112 | AR45: 43314 | AS45: 44591 | AT45: 1277 | AU45: 44203 | AV45: 3157 | AW45: 7746.2 | AX45: 1650 | AY45: 125 | AZ45: 291 | BA45: 1453.23 | BB45: 11265.43 | BC45: 1689.81 | BD45: 12955.24 | BE45: 45748 | BF45: 45838 | BG45: 35954 | BH45: 44591 | BI45: 8637 | BJ45: 9000 | BK45: -363 | BL45: 0.63 | BM45: 1.19 | BN45: 0 | BO45: 0 | BP45: 0 | BQ45: 0 | BR45: 0 | BS45: 0 | BT45: 0 | BU45: 0 | BV45: 0 | BW45: 0 | BX45: 0 | BY45: 3513.43 | BZ45: 0 | CA45: 0 | CB45: 0 | CC45: 0 | CD45: 0 | CE45: 0 | CF45: 0 | CG45: 0 | CH45: 12955.24 | CI45: 1689.81 | CJ45: 11265.43 | CK45: 8.82 | CL45: 0 | CM45: 0 | CN45: 0 | CO45: 100 | CQ45: 0 | CR45: 0 | CS45: 0 | CT45: 921 | CU45: 47238 | CV45: 47238 | CW45: 180388 | CX45: Active | CY45: Name 1 | CZ45: 1640.52 | DA45: 3098.76 | DB45: -779.88 | DC45: 0.55 | DD45: 0 | DE45: 0
A46: Company D | B46: 43862 | C46: Business Unit 3 | D46: Division 3 | E46: Cost Centre 3 | F46: RICHARDS BAY | G46: KWAZULU NATAL | H46: Manager 2 | I46: 43877 | J46: 43878 | K46: =J46-I46 -> 1 | L46: 1 | M46: =K46-L46 -> 0 | N46: 43876 | O46: 44023 | P46: =O46-N46 -> 147 | Q46: 90 | R46: =P46-Q46 -> 57 | S46: Reg 47 | T46: Contract 47 | U46: Long Term | V46: ONE TON LDV SINGLE CAB | W46: ISUZU | X46: D-MAX 250 HO FLEETSIDE (SAFETY) | Y46: 2024 | Z46: DIESEL | AA46: 2498 | AB46: 16 | AC46: 1 | AD46: 365565.22 | AE46: 71993.18 | AF46: 0.2 | AG46: 23204.92 | AH46: 3276.66 | AI46: 7.75 | AJ46: 168160 | AK46: 46 | AL46: 44023 | AM46: 45849 | AN46: 60 | AO46: 4500 | AP46: 216000 | AQ46: 46112 | AR46: 44532 | AS46: 46881 | AT46: 2349 | AU46: 46279 | AV46: 3306 | AW46: 5558.2 | AX46: 1845 | AY46: 125 | AZ46: 291 | BA46: 1089.17 | BB46: 8908.37 | BC46: 1336.26 | BD46: 10244.63 | BE46: 45748 | BF46: 45838 | BG46: 39656 | BH46: 46881 | BI46: 7225 | BJ46: 13500 | BK46: -6275 | BL46: 0.47 | BM46: 0.91 | BN46: 0 | BO46: 0 | BP46: 0 | BQ46: -385.91 | BR46: 0 | BS46: 0 | BT46: 0 | BU46: 0 | BV46: 0 | BW46: 0 | BX46: 0 | BY46: 5790.26 | BZ46: 0 | CA46: 0 | CB46: 0 | CC46: 0 | CD46: 0 | CE46: 0 | CF46: 0 | CG46: 0 | CH46: 7285.97 | CI46: 950.35 | CJ46: 6335.62 | CK46: 2.7 | CL46: 0 | CM46: 0 | CN46: 0 | CO46: 100 | CQ46: 0 | CR46: 0 | CS46: 0 | CT46: -18792 | CU46: 46873 | CV46: 46873 | CW46: 216602 | CX46: Active | CY46: Name 1 | CZ46: 1655.58 | DA46: 0 | DB46: -9360.3 | DC46: 0.41 | DD46: -2572.75 | DE46: -2958.66
A47: Company D | B47: 43862 | C47: Business Unit 1 | D47: Division 1 | E47: Cost Centre 1 | F47: RICHARDS BAY | G47: KWAZULU NATAL | H47: Manager 3 | I47: 43878 | J47: 43879 | K47: =J47-I47 -> 1 | L47: 1 | M47: =K47-L47 -> 0 | N47: 43877 | O47: 43902 | P47: =O47-N47 -> 25 | Q47: 90 | R47: =P47-Q47 -> -65 | S47: Reg 48 | T47: Contract 48 | U47: Long Term | V47: ONE TON LDV SINGLE CAB | W47: ISUZU | X47: D-MAX 250 HO FLEETSIDE (SAFETY) | Y47: 2024 | Z47: DIESEL | AA47: 2498 | AB47: 16 | AC47: 1 | AD47: 365565.22 | AE47: 71993.18 | AF47: 0.2 | AG47: 17942.97 | AH47: 1986 | AI47: 7.75 | AJ47: 168160 | AK47: 46 | AL47: 43902 | AM47: 45728 | AN47: 60 | AO47: 5000 | AP47: 220000 | AQ47: 46112 | AR47: 25619 | AS47: 27788 | AT47: 2169 | AU47: 27181 | AV47: 1942 | AW47: 5676.2 | AX47: 2000 | AY47: 125 | AZ47: 291 | BA47: 1089.17 | BB47: 9181.37 | BC47: 1377.21 | BD47: 10558.58 | BE47: 45748 | BF47: 45838 | BG47: 21788 | BH47: 27788 | BI47: 6000 | BJ47: 15000 | BK47: -9000 | BL47: 0.46 | BM47: 0.9 | BN47: 0 | BO47: 0 | BP47: 0 | BQ47: -540 | BR47: 0 | BS47: 0 | BT47: 0 | BU47: 0 | BV47: 0 | BW47: 0 | BX47: 0 | BY47: 4864.61 | BZ47: 0 | CA47: 114 | CB47: 0 | CC47: 0 | CD47: 0 | CE47: 0 | CF47: 0 | CG47: 0 | CH47: 6418.58 | CI47: 837.21 | CJ47: 5581.37 | CK47: 2.57 | CL47: 0 | CM47: 0 | CN47: 0 | CO47: 100 | CQ47: 0 | CR47: 0 | CS47: 0 | CT47: -45284 | CU47: 46752 | CV47: 46752 | CW47: 220607 | CX47: Active | CY47: Name 1 | CZ47: 4370.4 | DA47: 0 | DB47: -22484 | DC47: 0.4 | DD47: -3600 | DE47: -4140
... A297: Company E | B297: 44105 | C297: Business Unit 1 | D297: Division 3 | E297: Cost Centre 3 | F297: CAPE TOWN | G297: WESTERN CAPE | H297: Manager 1 | I297: 44128 | J297: 44131 | K297: =J297-I297 -> 3 | L297: 1 | M297: =K297-L297 -> 2 | N297: 44111 | O297: 44152 | P297: =O297-N297 -> 41 | Q297: 90 | R297: =P297-Q297 -> -49 | S297: Reg 298 | T297: Contract 298 | U297: Long Term | V297: MINIBUS | W297: HYUNDAI | X297: H1 2.5 VGTi 9-SEATER BUS AT | Y297: 2020 | Z297: DIESEL | AA297: 2498 | AB297: 16 | AC297: 0 | AD297: 363391.3 | AE297: 66699.78 | AF297: 0.18 | AG297: 16066.64 | AH297: 5277.5 | AI297: 7.75 | AJ297: 223010 | AK297: 38 | AL297: 44013 | AM297: 45978 | AN297: 60 | AO297: 1500 | AP297: 90000 | AQ297: 46173 | AR297: 38146 | AS297: 38332 | AT297: 186 | AU297: 36873 | AV297: 615 | AW297: 8404.41 | AX297: 646.85 | AY297: 98.45 | AZ297: 291 | BA297: 1441.63 | BB297: 10882.34 | BC297: 1632.35 | BD297: 12514.69 | BE297: 45748 | BF297: 45838 | BG297: 35705 | BH297: 38332 | BI297: 2627 | BJ297: 4500 | BK297: -1873 | BL297: 1.5 | BM297: 1.5 | BN297: 0 | BO297: 0 | BP297: 0 | BQ297: -120.81 | BR297: 0 | BS297: 0 | BT297: 0 | BU297: 0 | BV297: 0 | BW297: 0 | BX297: 0 | BY297: 1069.45 | BZ297: 0 | CA297: 0 | CB297: 0 | CC297: 0 | CD297: 0 | CE297: 0 | CF297: 0 | CG297: 0 | CH297: 11588.49 | CI297: 1511.54 | CJ297: 10076.95 | CK297: 54.18 | CL297: 0 | CM297: 0 | CN297: 0 | CO297: 100 | CQ297: 0 | CR297: 0 | CS297: 0 | CT297: -53127 | CU297: 45838 | CV297: 45838 | CW297: 91459 | CX297: Active | CY297: Name 2 | CZ297: 343.2 | DA297: 343.2 | DB297: -21069.32 | DC297: 0.43 | DD297: -805.39 | DE297: -926.2
A298: Company E | B298: 44105 | C298: Business Unit 2 | D298: Division 1 | E298: Cost Centre 1 | F298: CAPE TOWN | G298: WESTERN CAPE | H298: Manager 2 | I298: 44129 | J298: 44130 | K298: =J298-I298 -> 1 | L298: 1 | M298: =K298-L298 -> 0 | N298: 44112 | O298: 44304 | P298: =O298-N298 -> 192 | Q298: 90 | R298: =P298-Q298 -> 102 | S298: Reg 299 | T298: Contract 299 | U298: Long Term | V298: MINIBUS | W298: TOYOTA | X298: QUANTUM 2.8 GL LWB 14 SEATER | Y298: 2020 | Z298: DIESEL | AA298: 2798 | AB298: 16 | AC298: 9 | AD298: 363391.3 | AE298: 66699.78 | AF298: 0.18 | AG298: 0 | AH298: 0 | AI298: 7.75 | AL298: 44013 | AM298: 46130 | AN298: 60 | AO298: 197 | AP298: 46404 | AQ298: 46022 | AR298: 47845 | AS298: 47853 | AT298: 8 | AU298: 46404 | AV298: 787 | AW298: 666.34 | AX298: 85.07 | AY298: 16.3 | AZ298: 28.7 | BA298: 142.93 | BB298: 939.34 | BC298: 140.9 | BD298: 1080.24 | BE298: 45748 | BF298: 45811 | BG298: 42028 | BH298: 47853 | BI298: 5825 | BJ298: 4197 | BK298: 1628 | BL298: 0.5 | BM298: 2.62 | BN298: 814 | BO298: 4265.36 | BP298: 5079.36 | BQ298: 761.9 | BR298: 5841.26 | BS298: 2500 | BT298: 0 | BU298: 0 | BV298: 0 | BW298: 0 | BX298: 0 | BY298: 0 | CC298: 400 | CD298: 0 | CE298: 2900 | CF298: 375 | CG298: 3275 | CH298: 10196.5 | CI298: 1277.8 | CJ298: 8918.7 | CK298: 1114.84 | CL298: 20 | CM298: 0 | CN298: 0 | CO298: 100 | CQ298: 0 | CR298: 0 | CS298: 0 | CT298: -71793 | CU298: 45811 | CV298: 45811 | CW298: 47853 | CX298: Active | CY298: Name 2 | CZ298: 814 | DA298: 4265.36 | DB298: -28726.47 | DC298: 0.43 | DD298: 0 | DE298: 0
A299: Company E | B299: 44105 | C299: Business Unit 3 | D299: Division 2 | E299: Cost Centre 2 | F299: CAPE TOWN | G299: WESTERN CAPE | H299: Manager 3 | I299: 44130 | J299: 44131 | K299: =J299-I299 -> 1 | L299: 1 | M299: =K299-L299 -> 0 | N299: 44113 | O299: 44154 | P299: =O299-N299 -> 41 | Q299: 90 | R299: =P299-Q299 -> -49 | S299: Reg 300 | T299: Contract 300 | U299: Long Term | V299: SEDAN | W299: NISSAN | X299: ALMERA 1.5 ACENTA | Y299: 2020 | Z299: PETROL | AA299: 1498 | AB299: 16 | AC299: 11 | AD299: 190240.52 | AE299: 38683.01 | AF299: 0.2 | AG299: 20911.68 | AH299: 4403.5 | AI299: 7.75 | AJ299: 84516.68 | AK299: 98.52 | AL299: 44013 | AM299: 45980 | AN299: 60 | AO299: 1400 | AP299: 49731 | AQ299: 46173 | AR299: 45560 | AS299: 46178 | AT299: 618 | AU299: 44749 | AV299: 746 | AW299: 1771.15 | AX299: 1443 | AY299: 115 | AZ299: 291 | BA299: 1154.67 | BB299: 4774.82 | BC299: 716.22 | BD299: 5491.04 | BE299: 45748 | BF299: 45838 | BG299: 43375 | BH299: 46178 | BI299: 2803 | BJ299: 4200 | BK299: -1397 | BL299: 0.57 | BM299: 2.01 | BN299: 0 | BO299: 0 | BP299: 0 | BQ299: -104.78 | BR299: 0 | BS299: 0 | BT299: 0 | BU299: 0 | BV299: 0 | BW299: 0 | BX299: 0 | BY299: 2045.25 | BZ299: 0 | CA299: 0 | CB299: 0 | CC299: 0 | CD299: 0 | CE299: 0 | CF299: 0 | CG299: 0 | CH299: 4687.76 | CI299: 611.44 | CJ299: 4076.32 | CK299: 6.6 | CL299: 0 | CM299: 0 | CN299: 0 | CO299: 100 | CQ299: 0 | CR299: 0 | CS299: 0 | CT299: -39251 | CU299: 45930 | CV299: 45930 | CW299: 51160 | CX299: Active | CY299: Name 2 | CZ299: 1073.92 | DA299: 2858.8 | DB299: -18176.77 | DC299: 0.5 | DD299: -698.5 | DE299: -803.28
A300: Company F | B300: 44105 | C300: Business Unit 1 | D300: Division 3 | E300: Cost Centre 3 | F300: CAPE TOWN | G300: WESTERN CAPE | H300: Manager 1 | I300: 44131 | J300: 44132 | K300: =J300-I300 -> 1 | L300: 1 | M300: =K300-L300 -> 0 | N300: 44114 | O300: 44155 | P300: =O300-N300 -> 41 | Q300: 90 | R300: =P300-Q300 -> -49 | S300: Reg 301 | T300: Contract 301 | U300: Long Term | V300: ONE TON LDV SINGLE CAB | W300: ISUZU | X300: D-MAX 250 HO FLEETSIDE (SAFETY) | Y300: 2020 | Z300: DIESEL | AA300: 2498 | AB300: 16 | AC300: 5 | AD300: 291043.48 | AE300: 51971.57 | AF300: 0.18 | AG300: 19591.75 | AH300: 1881.5 | AI300: 7.75 | AJ300: 130970 | AK300: 45 | AL300: 44044 | AM300: 45981 | AN300: 60 | AO300: 2000 | AP300: 120000 | AQ300: 46234 | AR300: 51365 | AS300: 52818 | AT300: 1453 | AU300: 51380 | AV300: 871 | AW300: 4218.38 | AX300: 761 | AY300: 125 | AZ300: 291 | BA300: 1234.38 | BB300: 6629.76 | BC300: 994.46 | BD300: 7624.22 | BE300: 45748 | BF300: 45838 | BG300: 48300 | BH300: 52818 | BI300: 4518 | BJ300: 6000 | BK300: -1482 | BL300: 0.45 | BM300: 1.68 | BN300: 0 | BO300: 0 | BP300: 0 | BQ300: -84.47 | BR300: 0 | BS300: 0 | BT300: 0 | BU300: 0 | BV300: 0 | BW300: 0 | BX300: 0 | BY300: 5505.25 | BZ300: 0 | CA300: 0 | CB300: 0 | CC300: 0 | CD300: 0 | CE300: 0 | CF300: 0 | CG300: 0 | CH300: 6976.59 | CI300: 909.99 | CJ300: 6066.6 | CK300: 4.18 | CL300: 0 | CM300: 0 | CN300: 0 | CO300: 100 | CQ300: 0 | CR300: 0 | CS300: 0 | CT300: -66620 | CU300: 45869 | CV300: 45869 | CW300: 121438 | CX300: Active | CY300: Name 2 | CZ300: 0 | DA300: 0 | DB300: -23328.32 | DC300: 0.38 | DD300: -563.16 | DE300: -647.63
A301: Company F | B301: 44105 | C301: Business Unit 2 | D301: Division 1 | E301: Cost Centre 1 | F301: CAPE TOWN | G301: WESTERN CAPE | H301: Manager 2 | I301: 44132 | J301: 44135 | K301: =J301-I301 -> 3 | L301: 1 | M301: =K301-L301 -> 2 | N301: 44114 | O301: 44156 | P301: =O301-N301 -> 42 | Q301: 90 | R301: =P301-Q301 -> -48 | S301: Reg 302 | T301: Contract 302 | U301: Long Term | V301: ONE TON LDV SINGLE CAB | W301: ISUZU | X301: D-MAX 250 HO FLEETSIDE (SAFETY) | Y301: 2020 | Z301: DIESEL | AA301: 2498 | AB301: 16 | AC301: 6 | AD301: 291043.48 | AE301: 51971.57 | AF301: 0.18 | AG301: 19015.91 | AH301: 1239.5 | AI301: 7.75 | AJ301: 108212.98 | AK301: 82.76 | AL301: 44044 | AM301: 45982 | AN301: 60 | AO301: 1500 | AP301: 96929 | AQ301: 46234 | AR301: 89954 | AS301: 89954 | AT301: 1 | AU301: 88514 | AV301: 1500 | AW301: 4060.76 | AX301: 571 | AY301: 125 | AZ301: 291 | BA301: 1234.38 | BB301: 6282.14 | BC301: 942.32 | BD301: 7224.46 | BE301: 45748 | BF301: 45838 | BG301: 88538 | BH301: 89954 | BI301: 1416 | BJ301: 4500 | BK301: -3084 | BL301: 0.44 | BM301: 1.62 | BN301: 0 | BO301: 0 | BP301: 0 | BQ301: -175.79 | BR301: 0 | BS301: 0 | BT301: 0 | BU301: 0 | BV301: 0 | BW301: 0 | BX301: 0 | BY301: 0 | BZ301: 0 | CA301: 0 | CB301: 0 | CC301: 0 | CD301: 0 | CE301: 0 | CF301: 0 | CG301: 0 | CH301: 5876.75 | CI301: 766.53 | CJ301: 5110.22 | CK301: 5110.22 | CL301: 0 | CM301: 0 | CN301: 0 | CO301: 100 | CQ301: 0 | CR301: 0 | CS301: 0 | CT301: 14 | CU301: 45869 | CV301: 45869 | CW301: 98369 | CX301: Active | CY301: Name 2 | CZ301: 4465.19 | DA301: 22372.27 | DB301: -4154.74 | DC301: 0.38 | DD301: -1171.92 | DE301: -1347.71
A302: Company A | B302: 44136 | C302: Business Unit 3 | D302: Division 2 | E302: Cost Centre 2 | F302: CAPE TOWN | G302: WESTERN CAPE | H302: Manager 3 | I302: 44164 | J302: 44165 | K302: =J302-I302 -> 1 | L302: 1 | M302: =K302-L302 -> 0 | N302: 44146 | O302: 44277 | P302: =O302-N302 -> 131 | Q302: 90 | R302: =P302-Q302 -> 41 | S302: Reg 303 | T302: Contract 303 | U302: Long Term | V302: ONE TON LDV SINGLE CAB | W302: ISUZU | X302: D-MAX 250 HO FLEETSIDE (SAFETY) | Y302: 2020 | Z302: DIESEL | AA302: 2498 | AB302: 16 | AC302: 5 | AD302: 291043.48 | AE302: 51971.57 | AF302: 0.18 | AG302: 19462.52 | AH302: 1881.5 | AI302: 7.75 | AJ302: 130970 | AK302: 45 | AL302: 44277 | AM302: 46103 | AN302: 60 | AO302: 1500 | AP302: 90000 | AQ302: 46234 | AR302: 60867 | AS302: 61365 | AT302: 498 | AU302: 59925 | AV302: 1016 | AW302: 4005.47 | AX302: 570.77 | AY302: 125 | AZ302: 291 | BA302: 1444.7 | BB302: 6436.94 | BC302: 965.54 | BD302: 7402.48 | BE302: 45748 | BF302: 45838 | BG302: 58459 | BH302: 61365 | BI302: 2906 | BJ302: 4500 | BK302: -1594 | BL302: 0.45 | BM302: 2.25 | BN302: 0 | BO302: 0 | BP302: 0 | BQ302: -90.86 | BR302: 0 | BS302: 0 | BT302: 0 | BU302: 0 | BV302: 0 | BW302: 0 | BX302: 0 | BY302: 1444.3 | BZ302: 0 | CA302: 0 | CB302: 0 | CC302: 0 | CD302: 0 | CE302: 0 | CF302: 0 | CG302: 0 | CH302: 6705.9 | CI302: 874.68 | CJ302: 5831.22 | CK302: 11.71 | CL302: 0 | CM302: 0 | CN302: 0 | CO302: 100 | CQ302: 0 | CR302: 0 | CS302: 0 | CT302: -28575 | CU302: 45869 | CV302: 45869 | CW302: 91440 | CX302: Active | CY302: Name 2 | CZ302: 0 | DA302: 0 | DB302: -9760.47 | DC302: 0.38 | DD302: -605.72 | DE302: -696.58
A303: Company A | B303: 44136 | C303: Business Unit 1 | D303: Division 3 | E303: Cost Centre 3 | F303: CAPE TOWN | G303: WESTERN CAPE | H303: Manager 1 | I303: 44165 | J303: 44167 | K303: =J303-I303 -> 2 | L303: 1 | M303: =K303-L303 -> 1 | N303: 44148 | O303: 44278 | P303: =O303-N303 -> 130 | Q303: 90 | R303: =P303-Q303 -> 40 | S303: Reg 304 | T303: Contract 304 | U303: Long Term | V303: SEDAN | W303: NISSAN | X303: ALMERA 1.5 ACENTA | Y303: 2020 | Z303: PETROL | AA303: 1498 | AB303: 16 | AC303: 5 | AD303: 190240.52 | AE303: 38683.01 | AF303: 0.2 | AG303: 20141.64 | AH303: 1587.5 | AI303: 7.75 | AJ303: 77999 | AK303: 41 | AL303: 44278 | AM303: 46104 | AN303: 60 | AO303: 1400 | AP303: 84000 | AQ303: 46234 | AR303: 51822 | AS303: 52757 | AT303: 935 | AU303: 51339 | AV303: 870 | AW303: 3129.99 | AX303: 497.19 | AY303: 75 | AZ303: 291 | BA303: 1154.67 | BB303: 5147.85 | BC303: 772.18 | BD303: 5920.03 | BE303: 45748 | BF303: 45838 | BG303: 50555 | BH303: 52757 | BI303: 2202 | BJ303: 4200 | BK303: -1998 | BL303: 0.42 | BM303: 1.69 | BN303: 0 | BO303: 0 | BP303: 0 | BQ303: -107.89 | BR303: 0 | BS303: 0 | BT303: 0 | BU303: 0 | BV303: 0 | BW303: 0 | BX303: 0 | BY303: 3058.35 | BZ303: 0 | CA303: 0 | CB303: 0 | CC303: 0 | CD303: 0 | CE303: 0 | CF303: 0 | CG303: 0 | CH303: 5092.86 | CI303: 664.29 | CJ303: 4428.57 | CK303: 4.74 | CL303: 0 | CM303: 0 | CN303: 0 | CO303: 100 | CQ303: 0 | CR303: 0 | CS303: 0 | CT303: -31261 | CU303: 45869 | CV303: 45869 | CW303: 85418 | CX303: Active | CY303: Name 2 | CZ303: 0 | DA303: 0 | DB303: -10281.26 | DC303: 0.36 | DD303: -719.28 | DE303: -827.17
A304: Company A | B304: 44136 | C304: Business Unit 2 | D304: Division 1 | E304: Cost Centre 1 | F304: CAPE TOWN | G304: WESTERN CAPE | H304: Manager 2 | I304: 44158 | J304: 44162 | K304: =J304-I304 -> 4 | L304: 1 | M304: =K304-L304 -> 3 | N304: 44149 | O304: 44279 | P304: =O304-N304 -> 130 | Q304: 90 | R304: =P304-Q304 -> 40 | S304: Reg 305 | T304: Contract 305 | U304: Long Term | V304: ONE TON LDV DOUBLE CAB | W304: FORD | X304: RANGER 2.2 TDCI XL 4X2 D CAB | Y304: 2020 | Z304: DIESEL | AA304: 2198 | AB304: 16 | AC304: 4 | AD304: 387391 | AE304: 40292 | AF304: 0.1 | AG304: 30780.28 | AH304: 2241.5 | AI304: 7.75 | AJ304: 147209 | AK304: 38 | AL304: 44279 | AM304: 46105 | AN304: 60 | AO304: 3000 | AP304: 180000 | AQ304: 46234 | AR304: 71986 | AS304: 72586 | AT304: 600 | AU304: 71112 | AV304: 1205 | AW304: 6359.95 | AX304: 1388.97 | AY304: 125 | AZ304: 291 | BA304: 1254.3 | BB304: 9419.22 | BC304: 1412.88 | BD304: 10832.1 | BE304: 45748 | BF304: 45838 | BG304: 70665 | BH304: 72586 | BI304: 1921 | BJ304: 9000 | BK304: -7079 | BL304: 0.47 | BM304: 1.54 | BN304: 0 | BO304: 0 | BP304: 0 | BQ304: -488.45 | BR304: 0 | BS304: 0 | BT304: 0 | BU304: 0 | BV304: 0 | BW304: 0 | BX304: 0 | BY304: 1074.55 | BZ304: 0 | CA304: 0 | CB304: 0 | CC304: 0 | CD304: 0 | CE304: 0 | CF304: 0 | CG304: 0 | CH304: 7087.31 | CI304: 924.43 | CJ304: 6162.88 | CK304: 10.27 | CL304: 0 | CM304: 0 | CN304: 0 | CO304: 100 | CQ304: 0 | CR304: 0 | CS304: 0 | CT304: -105888 | CU304: 45869 | CV304: 45869 | CW304: 181474 | CX304: Active | CY304: Name 2 | CZ304: 761.87 | DA304: 2496.34 | DB304: -45680.09 | DC304: 0.46 | DD304: -3256.34 | DE304: -3744.79
A305: Company B | B305: 44136 | C305: Business Unit 3 | D305: Division 2 | E305: Cost Centre 2 | F305: CAPE TOWN | G305: WESTERN CAPE | H305: Manager 3 | I305: 44136 | J305: 44137 | K305: =J305-I305 -> 1 | L305: 1 | M305: =K305-L305 -> 0 | N305: 44150 | O305: 44278 | P305: =O305-N305 -> 128 | Q305: 90 | R305: =P305-Q305 -> 38 | S305: Reg 306 | T305: Contract 306 | U305: Long Term | V305: ONE TON LDV DOUBLE CAB | W305: FORD | X305: RANGER 2.2 TDCI XL 4X2 D CAB | Y305: 2020 | Z305: DIESEL | AA305: 2198 | AB305: 16 | AC305: 6 | AD305: 399186.96 | AE305: 52087.96 | AF305: 0.13 | AG305: 23532.42 | AH305: 2241.5 | AI305: 7.75 | AJ305: 151691 | AK305: 38 | AL305: 44278 | AM305: 46104 | AN305: 60 | AO305: 2000 | AP305: 120000 | AQ305: 46234 | AR305: 89005 | AS305: 90002 | AT305: 997 | AU305: 88558 | AV305: 1501 | AW305: 6156.53 | AX305: 852.87 | AY305: 125 | AZ305: 291 | BA305: 1254.3 | BB305: 8679.7 | BC305: 1301.96 | BD305: 9981.66 | BE305: 45748 | BF305: 45838 | BG305: 86046 | BH305: 90002 | BI305: 3956 | BJ305: 6000 | BK305: -2044 | BL305: 0.49 | BM305: 2.5 | BN305: 0 | BO305: 0 | BP305: 0 | BQ305: -131.84 | BR305: 0 | BS305: 0 | BT305: 0 | BU305: 0 | BV305: 0 | BW305: 0 | BX305: 0 | BY305: 2419.34 | BZ305: 0 | CA305: 0 | CB305: 0 | CC305: 0 | CD305: 0 | CE305: 0 | CF305: 0 | CG305: 0 | CH305: 8970.9 | CI305: 1170.12 | CJ305: 7800.78 | CK305: 7.82 | CL305: 0 | CM305: 0 | CN305: 0 | CO305: 100 | CQ305: 0 | CR305: 0 | CS305: 0 | CT305: -29442 | CU305: 45869 | CV305: 45869 | CW305: 121444 | CX305: Active | CY305: Name 2 | CZ305: 1442.59 | DA305: 7451.92 | DB305: -12839.02 | DC305: 0.43 | DD305: -878.92 | DE305: -1010.76
A306: Company B | B306: 44136 | C306: Business Unit 1 | D306: Division 3 | E306: Cost Centre 3 | F306: CAPE TOWN | G306: WESTERN CAPE | H306: Manager 1 | I306: 44137 | J306: 44138 | K306: =J306-I306 -> 1 | L306: 1 | M306: =K306-L306 -> 0 | N306: 44151 | O306: 44281 | P306: =O306-N306 -> 130 | Q306: 90 | R306: =P306-Q306 -> 40 | S306: Reg 307 | T306: Contract 307 | U306: Long Term | V306: SEDAN | W306: NISSAN | X306: ALMERA 1.5 ACENTA | Y306: 2020 | Z306: PETROL | AA306: 1498 | AB306: 16 | AC306: 1 | AD306: 190240.52 | AE306: 38683.01 | AF306: 0.2 | AG306: 20125.56 | AH306: 1677.5 | AI306: 7.75 | AJ306: 77999 | AK306: 41 | AL306: 44281 | AM306: 46107 | AN306: 60 | AO306: 1400 | AP306: 84000 | AQ306: 46234 | AR306: 26729 | AS306: 27051 | AT306: 322 | AU306: 25635 | AV306: 434 | AW306: 3122.51 | AX306: 497.19 | AY306: 75 | AZ306: 291 | BA306: 1154.67 | BB306: 5140.37 | BC306: 771.06 | BD306: 5911.43 | BE306: 45748 | BF306: 45838 | BG306: 25986 | BH306: 27051 | BI306: 1065 | BJ306: 4200 | BK306: -3135 | BL306: 0.42 | BM306: 1.69 | BN306: 0 | BO306: 0 | BP306: 0 | BQ306: -169.29 | BR306: 0 | BS306: 0 | BT306: 0 | BU306: 0 | BV306: 0 | BW306: 0 | BX306: 0 | BY306: 0 | BZ306: 0 | CA306: 0 | CB306: 0 | CC306: 0 | CD306: 0 | CE306: 0 | CF306: 0 | CG306: 0 | CH306: 4613.54 | CI306: 601.77 | CJ306: 4011.77 | CK306: 12.46 | CL306: 0 | CM306: 0 | CN306: 0 | CO306: 100 | CQ306: 0 | CR306: 0 | CS306: 0 | CT306: -56965 | CU306: 45869 | CV306: 45869 | CW306: 85416 | CX306: Active | CY306: Name 2 | CZ306: 0 | DA306: 0 | DB306: -18877.6 | DC306: 0.36 | DD306: -1128.6 | DE306: -1297.89
A307: Company B | B307: 44136 | C307: Business Unit 2 | D307: Division 1 | E307: Cost Centre 1 | F307: CAPE TOWN | G307: WESTERN CAPE | H307: Manager 2 | I307: 44138 | J307: 44143 | K307: =J307-I307 -> 5 | L307: 1 | M307: =K307-L307 -> 4 | N307: 44152 | O307: 44282 | P307: =O307-N307 -> 130 | Q307: 90 | R307: =P307-Q307 -> 40 | S307: Reg 308 | T307: Contract 308 | U307: Long Term | V307: MINIBUS | W307: TOYOTA | X307: QUANTUM 2.8 GL LWB 11 SEATER | Y307: 2020 | Z307: DIESEL | AA307: 2798 | AB307: 16 | AC307: 2 | AD307: 190240.52 | AE307: 38683.01 | AF307: 0.2 | AG307: 26209.53 | AH307: 4314.5 | AI307: 7.75 | AJ307: 214025 | AK307: 39 | AL307: 44282 | AM307: 46108 | AN307: 60 | AO307: 1400 | AP307: 84000 | AQ307: 46234 | AR307: 11536 | AS307: 11994 | AT307: 458 | AU307: 10536 | AV307: 179 | AW307: 7729.71 | AX307: 603.74 | AY307: 175 | AZ307: 291 | BA307: 1426.43 | BB307: 10225.88 | BC307: 1533.88 | BD307: 11759.76 | BE307: 45748 | BF307: 45838 | BG307: 11110 | BH307: 11994 | BI307: 884 | BJ307: 4200 | BK307: -3316 | BL307: 0.5 | BM307: 5.05 | BN307: 0 | BO307: 0 | BP307: 0 | BQ307: -213.88 | BR307: 0 | BS307: 0 | BT307: 0 | BU307: 0 | BV307: 0 | BW307: 0 | BX307: 0 | BY307: 1235.8 | BZ307: 0 | CA307: 0 | CB307: 0 | CC307: 0 | CD307: 0 | CE307: 0 | CF307: 0 | CG307: 0 | CH307: 10120 | CI307: 1320 | CJ307: 8800 | CK307: 19.21 | CL307: 0 | CM307: 0 | CN307: 0 | CO307: 100 | CQ307: 0 | CR307: 0 | CS307: 0 | CT307: -72064 | CU307: 45869 | CV307: 45869 | CW307: 85458 | CX307: Active | CY307: Name 2 | CZ307: 0 | DA307: 0 | DB307: -28597.41 | DC307: 0.43 | DD307: -1425.88 | DE307: -1639.76
A308: Company B | B308: 44136 | C308: Business Unit 3 | D308: Division 2 | E308: Cost Centre 2 | F308: CAPE TOWN | G308: WESTERN CAPE | H308: Manager 3 | I308: 44139 | J308: 44140 | K308: =J308-I308 -> 1 | L308: 1 | M308: =K308-L308 -> 0 | N308: 44153 | O308: 44283 | P308: =O308-N308 -> 130 | Q308: 90 | R308: =P308-Q308 -> 40 | S308: Reg 309 | T308: Contract 309 | U308: Long Term | V308: MINIBUS | W308: TOYOTA | X308: QUANTUM 2.8 GL LWB 14 SEATER | Y308: 2020 | Z308: DIESEL | AA308: 2798 | AB308: 16 | AC308: 15 | AD308: 190240.52 | AE308: 38683.01 | AF308: 0.2 | AG308: 26653.55 | AH308: 2664.5 | AI308: 7.75 | AJ308: 315402 | AK308: 56 | AL308: 44283 | AM308: 46109 | AN308: 60 | AO308: 2000 | AP308: 120000 | AQ308: 46112 | AR308: 109029 | AS308: 111653 | AT308: 2624 | AU308: 110207 | AV308: 1868 | AW308: 6673.16 | AX308: 828.51 | AY308: 175 | AZ308: 291 | BA308: 1392.1 | BB308: 9359.77 | BC308: 1403.97 | BD308: 10763.74 | BE308: 45748 | BF308: 45838 | BG308: 101652 | BH308: 111653 | BI308: 10001 | BJ308: 6000 | BK308: 4001 | BL308: 0.47 | BM308: 2.52 | BN308: 1880.47 | BO308: 10082.52 | BP308: 11962.99 | BQ308: 1794.45 | BR308: 13757.44 | BS308: 1465 | BT308: 0 | BU308: 0 | BV308: 0 | BW308: 0 | BX308: 0 | BY308: 9641.5 | BZ308: 0 | CA308: 0 | CB308: 0 | CC308: 0 | CD308: 0 | CE308: 1465 | CF308: 219.75 | CG308: 1684.75 | CH308: 26205.93 | CI308: 3418.17 | CJ308: 22787.76 | CK308: 8.68 | CL308: 15 | CM308: 0 | CN308: 0 | CO308: 100 | CQ308: 0 | CR308: 0 | CS308: 0 | CT308: -7793 | CU308: 45869 | CV308: 45869 | CW308: 121446 | CX308: Active | CY308: Name 2 | CZ308: 7184.34 | DA308: 38513.64 | DB308: -8375.05 | DC308: 0.41 | DD308: 0 | DE308: 0
A309: Company C | B309: 44136 | C309: Business Unit 1 | D309: Division 3 | E309: Cost Centre 3 | F309: CAPE TOWN | G309: WESTERN CAPE | H309: Manager 1 | I309: 44140 | J309: 44141 | K309: =J309-I309 -> 1 | L309: 1 | M309: =K309-L309 -> 0 | N309: 44154 | O309: 44284 | P309: =O309-N309 -> 130 | Q309: 90 | R309: =P309-Q309 -> 40 | S309: Reg 310 | T309: Contract 310 | U309: Long Term | V309: MINIBUS | W309: TOYOTA | X309: QUANTUM 2.8 GL LWB 11 SEATER | Y309: 2020 | Z309: DIESEL | AA309: 2798 | AB309: 16 | AC309: 16 | AD309: 190240.52 | AE309: 38683.01 | AF309: 0.2 | AG309: 26486.43 | AH309: 4314.5 | AI309: 7.75 | AJ309: 252440 | AK309: 46 | AL309: 44284 | AM309: 46110 | AN309: 60 | AO309: 2500 | AP309: 150000 | AQ309: 46203 | AR309: 117032 | AS309: 121357 | AT309: 4325 | AU309: 119897 | AV309: 2032 | AW309: 7482.46 | AX309: 1078.1 | AY309: 175 | AZ309: 291 | BA309: 1426.43 | BB309: 10452.99 | BC309: 1567.95 | BD309: 12020.94 | BE309: 45748 | BF309: 45838 | BG309: 108451 | BH309: 121357 | BI309: 12906 | BJ309: 7500 | BK309: 5406 | BL309: 0.5 | BM309: 2.5 | BN309: 2703 | BO309: 13515 | BP309: 16218 | BQ309: 2432.7 | BR309: 18650.7 | BS309: 3941 | BT309: 0 | BU309: 0 | BV309: 0 | BW309: 0 | BX309: 0 | BY309: 15134.4 | BZ309: 0 | CA309: 0 | CB309: 0 | CC309: 0 | CD309: 0 | CE309: 3941 | CF309: 591.15 | CG309: 4532.15 | CH309: 35203.79 | CI309: 4591.8 | CJ309: 30611.99 | CK309: 7.08 | CL309: 19 | CM309: 0 | CN309: 0 | CO309: 100 | CQ309: 0 | CR309: 0 | CS309: 0 | CT309: -27603 | CU309: 45869 | CV309: 45869 | CW309: 151460 | CX309: Active | CY309: Name 2 | CZ309: 7730 | DA309: 38650 | DB309: -16121.21 | DC309: 0.43 | DD309: 0 | DE309: 0
A310: Company C | B310: 44136 | C310: Business Unit 2 | D310: Division 1 | E310: Cost Centre 1 | F310: SALDANHA | G310: WESTERN CAPE | H310: Manager 2 | I310: 44141 | J310: 44142 | K310: =J310-I310 -> 1 | L310: 1 | M310: =K310-L310 -> 0 | N310: 44155 | O310: 44285 | P310: =O310-N310 -> 130 | Q310: 90 | R310: =P310-Q310 -> 40 | S310: Reg 311 | T310: Contract 311 | U310: Long Term | V310: ONE TON LDV SINGLE CAB | W310: ISUZU | X310: D-MAX 250 HO FLEETSIDE (SAFETY) | Y310: 2020 | Z310: DIESEL | AA310: 2498 | AB310: 16 | AC310: 15.99 | AD310: 291043.48 | AE310: 52106.57 | AF310: 0.18 | AG310: 30373.32 | AH310: 1830 | AI310: 7.75 | AJ310: 130970 | AK310: 45 | AL310: 44285 | AM310: 46111 | AN310: 60 | AO310: 3000 | AP310: 180000 | AQ310: 46142 | AR310: 132468 | AS310: 137765 | AT310: 5297 | AU310: 136207 | AV310: 2309 | AW310: 4203.86 | AX310: 1096.54 | AY310: 125 | AZ310: 291 | BA310: 1185.78 | BB310: 6902.18 | BC310: 1035.33 | BD310: 7937.51 | BE310: 45748 | BF310: 45838 | BG310: 126822 | BH310: 137765 | BI310: 10943 | BJ310: 9000 | BK310: 1943 | BL310: 0.83 | BM310: 2.76 | BN310: 1612.69 | BO310: 5362.68 | BP310: 6975.37 | BQ310: 1046.31 | BR310: 8021.68 | BS310: 0 | BT310: 0 | BU310: 0 | BV310: 0 | BW310: 0 | BX310: 0 | BY310: 11452.05 | BZ310: 0 | CA310: 0 | CB310: 0 | CC310: 0 | CD310: 0 | CE310: 0 | CF310: 0 | CG310: 0 | CH310: 15959.19 | CI310: 2081.64 | CJ310: 13877.55 | CK310: 2.62 | CL310: 0 | CM310: 0 | CN310: 0 | CO310: 100 | CQ310: 0 | CR310: 0 | CS310: 0 | CT310: -40793 | CU310: 45869 | CV310: 45869 | CW310: 181558 | CX310: Active | CY310: Name 2 | CZ310: 18637.12 | DA310: 61175.45 | DB310: -22383.18 | DC310: 0.37 | DD310: 0 | DE310: 0
... A359: Company F | B359: 44166 | C359: Business Unit 1 | D359: Division 1 | E359: Cost Centre 1 | F359: CAPE TOWN | G359: WESTERN CAPE | H359: Manager 3 | I359: 44190 | J359: 44191 | K359: =J359-I359 -> 1 | L359: 1 | M359: =K359-L359 -> 0 | N359: 44538 | O359: 44699 | P359: =O359-N359 -> 161 | Q359: 90 | R359: =P359-Q359 -> 71 | S359: Reg 360 | T359: Contract 360 | U359: Long Term | V359: ONE TON LDV SINGLE CAB | W359: ISUZU | X359: D-MAX 250 HO FLEETSIDE (SAFETY) | Y359: 2021 | Z359: DIESEL | AA359: 2498 | AB359: 16 | AC359: 1 | AD359: 305826.09 | AE359: 47723.1 | AF359: 0.16 | AG359: 21113.78 | AH359: 2678.5 | AI359: 7.75 | AJ359: 137622 | AK359: 45 | AL359: 44699 | AM359: 46525 | AN359: 60 | AO359: 1500 | AP359: 90000 | AQ359: 45900 | AR359: 75859 | AS359: 77786 | AT359: 1927 | AU359: 76301 | AV359: 1496 | AW359: 4506.66 | AX359: 1029.13 | AY359: 125 | AZ359: 291 | BA359: 1185.5 | BB359: 7137.29 | BC359: 1070.59 | BD359: 8207.88 | BE359: 45748 | BF359: 45838 | BG359: 72136 | BH359: 77786 | BI359: 5650 | BJ359: 4500 | BK359: 1150 | BL359: 0.79 | BM359: 2.21 | BN359: 908.5 | BO359: 2541.5 | BP359: 3450 | BQ359: 517.5 | BR359: 3967.5 | BS359: 0 | BT359: 0 | BU359: 0 | BV359: 0 | BW359: 0 | BX359: 0 | BY359: 4129.34 | BZ359: 0 | CA359: 0 | CB359: 0 | CC359: 0 | CD359: 0 | CE359: 0 | CF359: 0 | CG359: 0 | CH359: 12175.38 | CI359: 1588.09 | CJ359: 10587.29 | CK359: 5.49 | CL359: 0 | CM359: 0 | CN359: 0 | CO359: 100 | CQ359: 0 | CR359: 0 | CS359: 0 | CT359: -1185 | CU359: 46112 | CV359: 46112 | CW359: 91485 | CX359: Active | CY359: Name 2 | CZ359: 6302.22 | DA359: 17623.22 | DB359: -5839.36 | DC359: 0.68 | DD359: 0 | DE359: 0

Sheet Pivot-Main

Sheet KPIs_Fleet Master Data
A1: Vehicle Fleet Master data
A2: - a record of all vehicle master data from inception of contracts that’s currently in fleet
A3: ='Test 4-Stats'!S1 -> Reg No | B3: ='Test 4-Stats'!Y1 -> Year | C3: ='Test 4-Stats'!W1 -> Make | D3: ='Test 4-Stats'!V1 -> Rate Category | E3: ='Test 4-Stats'!X1 -> Model | F3: {='Test 4-Stats'!Z1:AA1} -> Fuel Type | G3: Engine Capacity | H3: {='Test 4-Stats'!C1:H1} -> Business Unit | I3: Division/Depot/Department | J3: Cost Centre | K3: Area | L3: Province | M3: Responsible Manager | N3: {='Test 4-Stats'!AL1:AN1} -> Start Date | O3: End Date | P3: Contract Period | Q3: ='Test 4-Stats'!CX1 -> Deal Status
A4: ='Test 4-Stats'!S2 -> Reg 1 | B4: ='Test 4-Stats'!Y2 -> 2020 | C4: ='Test 4-Stats'!W2 -> NISSAN | D4: ='Test 4-Stats'!V2 -> HALF TON LDV | E4: ='Test 4-Stats'!X2 -> NP200 1.6 8V AC SAFETY PACK | F4: {='Test 4-Stats'!Z2:AA2} -> PETROL | G4: 1598 | H4: {='Test 4-Stats'!C2:H2} -> Business Unit 1 | I4: Division 1 | J4: Cost Centre 1 | K4: CAPE TOWN | L4: WESTERN CAPE | M4: Manager 1 | N4: {='Test 4-Stats'!AL2:AN2} -> 43886 | O4: 45713 | P4: 60 | Q4: ='Test 4-Stats'!CX2 -> Active
A5: ='Test 4-Stats'!S3 -> Reg 2 | B5: ='Test 4-Stats'!Y3 -> 2019 | C5: ='Test 4-Stats'!W3 -> ISUZU | D5: ='Test 4-Stats'!V3 -> ONE TON LDV SINGLE CAB | E5: ='Test 4-Stats'!X3 -> KB 250 D-TEQ FLEETSIDE (SAFETY) | F5: {='Test 4-Stats'!Z3:AA3} -> DIESEL | G5: 2498 | H5: {='Test 4-Stats'!C3:H3} -> Business Unit 2 | I5: Division 2 | J5: Cost Centre 2 | K5: ISANDO | L5: GAUTENG | M5: Manager 2 | N5: {='Test 4-Stats'!AL3:AN3} -> 43977 | O5: 45803 | P5: 60 | Q5: ='Test 4-Stats'!CX3 -> Active
A6: ='Test 4-Stats'!S4 -> Reg 3 | B6: ='Test 4-Stats'!Y4 -> 2019 | C6: ='Test 4-Stats'!W4 -> ISUZU | D6: ='Test 4-Stats'!V4 -> ONE TON LDV SINGLE CAB | E6: ='Test 4-Stats'!X4 -> KB 250 D-TEQ FLEETSIDE (SAFETY) | F6: {='Test 4-Stats'!Z4:AA4} -> DIESEL | G6: 2498 | H6: {='Test 4-Stats'!C4:H4} -> Business Unit 3 | I6: Division 3 | J6: Cost Centre 3 | K6: PRETORIA | L6: KWAZULU NATAL | M6: Manager 3 | N6: {='Test 4-Stats'!AL4:AN4} -> 43917 | O6: 45743 | P6: 60 | Q6: ='Test 4-Stats'!CX4 -> Active
A7: ='Test 4-Stats'!S5 -> Reg 4 | B7: ='Test 4-Stats'!Y5 -> 2019 | C7: ='Test 4-Stats'!W5 -> ISUZU | D7: ='Test 4-Stats'!V5 -> ONE TON LDV DOUBLE CAB | E7: ='Test 4-Stats'!X5 -> KB 250 D-TEQ HI-RIDER D/CAB | F7: {='Test 4-Stats'!Z5:AA5} -> DIESEL | G7: 2498 | H7: {='Test 4-Stats'!C5:H5} -> Business Unit 1 | I7: Division 1 | J7: Cost Centre 1 | K7: ISANDO | L7: GAUTENG | M7: Manager 1 | N7: {='Test 4-Stats'!AL5:AN5} -> 44040 | O7: 45866 | P7: 60 | Q7: ='Test 4-Stats'!CX5 -> Active
A8: ='Test 4-Stats'!S6 -> Reg 5 | B8: ='Test 4-Stats'!Y6 -> 2019 | C8: ='Test 4-Stats'!W6 -> ISUZU | D8: ='Test 4-Stats'!V6 -> ONE TON LDV SINGLE CAB | E8: ='Test 4-Stats'!X6 -> KB 250 D-TEQ FLEETSIDE (SAFETY) | F8: {='Test 4-Stats'!Z6:AA6} -> DIESEL | G8: 2498 | H8: {='Test 4-Stats'!C6:H6} -> Business Unit 2 | I8: Division 2 | J8: Cost Centre 2 | K8: ISANDO | L8: GAUTENG | M8: Manager 2 | N8: {='Test 4-Stats'!AL6:AN6} -> 43859 | O8: 45686 | P8: 60 | Q8: ='Test 4-Stats'!CX6 -> Active
A9: ='Test 4-Stats'!S7 -> Reg 6 | B9: ='Test 4-Stats'!Y7 -> 2019 | C9: ='Test 4-Stats'!W7 -> ISUZU | D9: ='Test 4-Stats'!V7 -> ONE TON LDV SINGLE CAB | E9: ='Test 4-Stats'!X7 -> KB 250 D-TEQ FLEETSIDE (SAFETY) | F9: {='Test 4-Stats'!Z7:AA7} -> DIESEL | G9: 2498 | H9: {='Test 4-Stats'!C7:H7} -> Business Unit 3 | I9: Division 3 | J9: Cost Centre 3 | K9: PARKTOWN | L9: GAUTENG | M9: Manager 3 | N9: {='Test 4-Stats'!AL7:AN7} -> 43884 | O9: 45711 | P9: 60 | Q9: ='Test 4-Stats'!CX7 -> Active
A10: ='Test 4-Stats'!S8 -> Reg 7 | B10: ='Test 4-Stats'!Y8 -> 2019 | C10: ='Test 4-Stats'!W8 -> ISUZU | D10: ='Test 4-Stats'!V8 -> ONE TON LDV SINGLE CAB | E10: ='Test 4-Stats'!X8 -> KB 250 D-TEQ FLEETSIDE (SAFETY) | F10: {='Test 4-Stats'!Z8:AA8} -> DIESEL | G10: 2498 | H10: {='Test 4-Stats'!C8:H8} -> Business Unit 1 | I10: Division 1 | J10: Cost Centre 1 | K10: MILL SITE | L10: GAUTENG | M10: Manager 1 | N10: {='Test 4-Stats'!AL8:AN8} -> 43861 | O10: 45688 | P10: 60 | Q10: ='Test 4-Stats'!CX8 -> Active
A11: ='Test 4-Stats'!S9 -> Reg 8 | B11: ='Test 4-Stats'!Y9 -> 2019 | C11: ='Test 4-Stats'!W9 -> ISUZU | D11: ='Test 4-Stats'!V9 -> ONE TON LDV SINGLE CAB | E11: ='Test 4-Stats'!X9 -> KB 250 D-TEQ FLEETSIDE (SAFETY) | F11: {='Test 4-Stats'!Z9:AA9} -> DIESEL | G11: 2498 | H11: {='Test 4-Stats'!C9:H9} -> Business Unit 2 | I11: Division 2 | J11: Cost Centre 2 | K11: MILL SITE | L11: GAUTENG | M11: Manager 2 | N11: {='Test 4-Stats'!AL9:AN9} -> 43862 | O11: 45689 | P11: 60 | Q11: ='Test 4-Stats'!CX9 -> Active
A12: ='Test 4-Stats'!S10 -> Reg 9 | B12: ='Test 4-Stats'!Y10 -> 2020 | C12: ='Test 4-Stats'!W10 -> ISUZU | D12: ='Test 4-Stats'!V10 -> ONE TON LDV SINGLE CAB | E12: ='Test 4-Stats'!X10 -> D-MAX 250 HO FLEETSIDE (SAFETY) | F12: {='Test 4-Stats'!Z10:AA10} -> DIESEL | G12: 2498 | H12: {='Test 4-Stats'!C10:H10} -> Business Unit 3 | I12: Division 3 | J12: Cost Centre 3 | K12: ERMELO | L12: MPUMALANGA | M12: Manager 3 | N12: {='Test 4-Stats'!AL10:AN10} -> 43863 | O12: 45690 | P12: 60 | Q12: ='Test 4-Stats'!CX10 -> Active
A13: ='Test 4-Stats'!S11 -> Reg 10 | B13: ='Test 4-Stats'!Y11 -> 2020 | C13: ='Test 4-Stats'!W11 -> ISUZU | D13: ='Test 4-Stats'!V11 -> ONE TON LDV DOUBLE CAB | E13: ='Test 4-Stats'!X11 -> D-MAX 250 HO HI-RIDER D/CAB | F13: {='Test 4-Stats'!Z11:AA11} -> DIESEL | G13: 2498 | H13: {='Test 4-Stats'!C11:H11} -> Business Unit 1 | I13: Division 1 | J13: Cost Centre 1 | K13: KAALFONTEIN | L13: GAUTENG | M13: Manager 1 | N13: {='Test 4-Stats'!AL11:AN11} -> 43864 | O13: 45691 | P13: 60 | Q13: ='Test 4-Stats'!CX11 -> Active
A14: ='Test 4-Stats'!S12 -> Reg 11 | B14: ='Test 4-Stats'!Y12 -> 2023 | C14: ='Test 4-Stats'!W12 -> ISUZU | D14: ='Test 4-Stats'!V12 -> ONE TON LDV DOUBLE CAB | E14: ='Test 4-Stats'!X12 -> D-MAX 250 HO HI-RIDER D/CAB | F14: {='Test 4-Stats'!Z12:AA12} -> DIESEL | G14: 2498 | H14: {='Test 4-Stats'!C12:H12} -> Business Unit 2 | I14: Division 2 | J14: Cost Centre 2 | K14: ELANDSFONTEIN | L14: GAUTENG | M14: Manager 2 | N14: {='Test 4-Stats'!AL12:AN12} -> 43986 | O14: 45812 | P14: 60 | Q14: ='Test 4-Stats'!CX12 -> Active
A15: ='Test 4-Stats'!S13 -> Reg 12 | B15: ='Test 4-Stats'!Y13 -> 2023 | C15: ='Test 4-Stats'!W13 -> ISUZU | D15: ='Test 4-Stats'!V13 -> ONE TON LDV DOUBLE CAB | E15: ='Test 4-Stats'!X13 -> D-MAX 250 HO HI-RIDER D/CAB | F15: {='Test 4-Stats'!Z13:AA13} -> DIESEL | G15: 2498 | H15: {='Test 4-Stats'!C13:H13} -> Business Unit 3 | I15: Division 3 | J15: Cost Centre 3 | K15: RICHARDS BAY | L15: KWAZULU NATAL | M15: Manager 3 | N15: {='Test 4-Stats'!AL13:AN13} -> 43866 | O15: 45693 | P15: 60 | Q15: ='Test 4-Stats'!CX13 -> Active
... A36: ='Test 4-Stats'!S34 -> Reg 35 | B36: ='Test 4-Stats'!Y34 -> 2024 | C36: ='Test 4-Stats'!W34 -> TOYOTA | D36: ='Test 4-Stats'!V34 -> MINIBUS | E36: ='Test 4-Stats'!X34 -> QUANTUM 2.5 D-4D 14-SEATER BUS | F36: {='Test 4-Stats'!Z34:AA34} -> DIESEL | G36: 2498 | H36: {='Test 4-Stats'!C34:H34} -> Business Unit 3 | I36: Division 2 | J36: Cost Centre 2 | K36: DURBAN | L36: KWAZULU NATAL | M36: Manager 2 | N36: {='Test 4-Stats'!AL34:AN34} -> 43889 | O36: 45716 | P36: 60 | Q36: ='Test 4-Stats'!CX34 -> Active
A37: ='Test 4-Stats'!S35 -> Reg 36 | B37: ='Test 4-Stats'!Y35 -> 2024 | C37: ='Test 4-Stats'!W35 -> TOYOTA | D37: ='Test 4-Stats'!V35 -> MINIBUS | E37: ='Test 4-Stats'!X35 -> QUANTUM 2.5 D-4D 14-SEATER BUS | F37: {='Test 4-Stats'!Z35:AA35} -> DIESEL | G37: 2498 | H37: {='Test 4-Stats'!C35:H35} -> Business Unit 1 | I37: Division 1 | J37: Cost Centre 1 | K37: DURBAN | L37: KWAZULU NATAL | M37: Manager 3 | N37: {='Test 4-Stats'!AL35:AN35} -> 43890 | O37: 2/29/2025 | P37: 60 | Q37: ='Test 4-Stats'!CX35 -> Active
A38: ='Test 4-Stats'!S36 -> Reg 37 | B38: ='Test 4-Stats'!Y36 -> 2024 | C38: ='Test 4-Stats'!W36 -> TOYOTA | D38: ='Test 4-Stats'!V36 -> MINIBUS | E38: ='Test 4-Stats'!X36 -> QUANTUM 2.5 D-4D 14-SEATER BUS | F38: {='Test 4-Stats'!Z36:AA36} -> DIESEL | G38: 2498 | H38: {='Test 4-Stats'!C36:H36} -> Business Unit 2 | I38: Division 2 | J38: Cost Centre 2 | K38: DURBAN | L38: KWAZULU NATAL | M38: Manager 1 | N38: {='Test 4-Stats'!AL36:AN36} -> 43891 | O38: 45717 | P38: 60 | Q38: ='Test 4-Stats'!CX36 -> Active
A39: ='Test 4-Stats'!S37 -> Reg 38 | B39: ='Test 4-Stats'!Y37 -> 2024 | C39: ='Test 4-Stats'!W37 -> HYUNDAI | D39: ='Test 4-Stats'!V37 -> MINIBUS | E39: ='Test 4-Stats'!X37 -> STARIA 2.2D EXECUTIVE 11 SEATER AT | F39: {='Test 4-Stats'!Z37:AA37} -> DIESEL | G39: 2198 | H39: {='Test 4-Stats'!C37:H37} -> Business Unit 3 | I39: Division 3 | J39: Cost Centre 3 | K39: RICHARDS BAY | L39: KWAZULU NATAL | M39: Manager 2 | N39: {='Test 4-Stats'!AL37:AN37} -> 43892 | O39: 45718 | P39: 60 | Q39: ='Test 4-Stats'!CX37 -> Active
A40: ='Test 4-Stats'!S38 -> Reg 39 | B40: ='Test 4-Stats'!Y38 -> 2024 | C40: ='Test 4-Stats'!W38 -> TOYOTA | D40: ='Test 4-Stats'!V38 -> MINIBUS | E40: ='Test 4-Stats'!X38 -> QUANTUM 2.5 D-4D 14-SEATER BUS | F40: {='Test 4-Stats'!Z38:AA38} -> DIESEL | G40: 2498 | H40: {='Test 4-Stats'!C38:H38} -> Business Unit 1 | I40: Division 1 | J40: Cost Centre 1 | K40: DURBAN | L40: KWAZULU NATAL | M40: Manager 3 | N40: {='Test 4-Stats'!AL38:AN38} -> 43893 | O40: 45719 | P40: 60 | Q40: ='Test 4-Stats'!CX38 -> Active
A41: ='Test 4-Stats'!S39 -> Reg 40 | B41: ='Test 4-Stats'!Y39 -> 2024 | C41: ='Test 4-Stats'!W39 -> ISUZU | D41: ='Test 4-Stats'!V39 -> ONE TON LDV SINGLE CAB | E41: ='Test 4-Stats'!X39 -> D-MAX 250 HO FLEETSIDE (SAFETY) | F41: {='Test 4-Stats'!Z39:AA39} -> DIESEL | G41: 2498 | H41: {='Test 4-Stats'!C39:H39} -> Business Unit 2 | I41: Division 2 | J41: Cost Centre 2 | K41: DURBAN | L41: KWAZULU NATAL | M41: Manager 1 | N41: {='Test 4-Stats'!AL39:AN39} -> 43986 | O41: 45812 | P41: 60 | Q41: ='Test 4-Stats'!CX39 -> Active
A42: ='Test 4-Stats'!S40 -> Reg 41 | B42: ='Test 4-Stats'!Y40 -> 2024 | C42: ='Test 4-Stats'!W40 -> FORD | D42: ='Test 4-Stats'!V40 -> ONE TON LDV DOUBLE CAB | E42: ='Test 4-Stats'!X40 -> RANGER 2.0 SiT D CAB BASE 4X2 | F42: {='Test 4-Stats'!Z40:AA40} -> DIESEL | G42: 1998 | H42: {='Test 4-Stats'!C40:H40} -> Business Unit 3 | I42: Division 3 | J42: Cost Centre 3 | K42: LADYSMITH | L42: KWAZULU NATAL | M42: Manager 2 | N42: {='Test 4-Stats'!AL40:AN40} -> 43895 | O42: 45721 | P42: 60 | Q42: ='Test 4-Stats'!CX40 -> Active
A43: ='Test 4-Stats'!S41 -> Reg 42 | B43: ='Test 4-Stats'!Y41 -> 2024 | C43: ='Test 4-Stats'!W41 -> FORD | D43: ='Test 4-Stats'!V41 -> ONE TON LDV DOUBLE CAB | E43: ='Test 4-Stats'!X41 -> RANGER 2.0 SiT D CAB BASE 4X2 | F43: {='Test 4-Stats'!Z41:AA41} -> DIESEL | G43: 1998 | H43: {='Test 4-Stats'!C41:H41} -> Business Unit 1 | I43: Division 1 | J43: Cost Centre 1 | K43: LADYSMITH | L43: KWAZULU NATAL | M43: Manager 3 | N43: {='Test 4-Stats'!AL41:AN41} -> 43896 | O43: 45722 | P43: 60 | Q43: ='Test 4-Stats'!CX41 -> Active
A44: ='Test 4-Stats'!S42 -> Reg 43 | B44: ='Test 4-Stats'!Y42 -> 2024 | C44: ='Test 4-Stats'!W42 -> FORD | D44: ='Test 4-Stats'!V42 -> ONE TON LDV DOUBLE CAB | E44: ='Test 4-Stats'!X42 -> RANGER 2.0 SiT D CAB BASE 4X2 | F44: {='Test 4-Stats'!Z42:AA42} -> DIESEL | G44: 1998 | H44: {='Test 4-Stats'!C42:H42} -> Business Unit 2 | I44: Division 2 | J44: Cost Centre 2 | K44: LADYSMITH | L44: KWAZULU NATAL | M44: Manager 1 | N44: {='Test 4-Stats'!AL42:AN42} -> 43897 | O44: 45723 | P44: 60 | Q44: ='Test 4-Stats'!CX42 -> Active
A45: ='Test 4-Stats'!S43 -> Reg 44 | B45: ='Test 4-Stats'!Y43 -> 2024 | C45: ='Test 4-Stats'!W43 -> FORD | D45: ='Test 4-Stats'!V43 -> ONE TON LDV DOUBLE CAB | E45: ='Test 4-Stats'!X43 -> RANGER 2.0 SiT D CAB BASE 4X2 | F45: {='Test 4-Stats'!Z43:AA43} -> DIESEL | G45: 1998 | H45: {='Test 4-Stats'!C43:H43} -> Business Unit 3 | I45: Division 3 | J45: Cost Centre 3 | K45: LADYSMITH | L45: KWAZULU NATAL | M45: Manager 2 | N45: {='Test 4-Stats'!AL43:AN43} -> 43898 | O45: 45724 | P45: 60 | Q45: ='Test 4-Stats'!CX43 -> Active
A46: ='Test 4-Stats'!S44 -> Reg 45 | B46: ='Test 4-Stats'!Y44 -> 2024 | C46: ='Test 4-Stats'!W44 -> FORD | D46: ='Test 4-Stats'!V44 -> ONE TON LDV DOUBLE CAB | E46: ='Test 4-Stats'!X44 -> RANGER 2.0 SiT D CAB BASE 4X2 | F46: {='Test 4-Stats'!Z44:AA44} -> DIESEL | G46: 1998 | H46: {='Test 4-Stats'!C44:H44} -> Business Unit 1 | I46: Division 1 | J46: Cost Centre 1 | K46: LADYSMITH | L46: KWAZULU NATAL | M46: Manager 3 | N46: {='Test 4-Stats'!AL44:AN44} -> 43899 | O46: 45725 | P46: 60 | Q46: ='Test 4-Stats'!CX44 -> Active
A47: ='Test 4-Stats'!S45 -> Reg 46 | B47: ='Test 4-Stats'!Y45 -> 2024 | C47: ='Test 4-Stats'!W45 -> FORD | D47: ='Test 4-Stats'!V45 -> ONE TON LDV DOUBLE CAB | E47: ='Test 4-Stats'!X45 -> RANGER 2.0 SiT D CAB BASE 4X2 | F47: {='Test 4-Stats'!Z45:AA45} -> DIESEL | G47: 1998 | H47: {='Test 4-Stats'!C45:H45} -> Business Unit 2 | I47: Division 2 | J47: Cost Centre 2 | K47: LADYSMITH | L47: KWAZULU NATAL | M47: Manager 1 | N47: {='Test 4-Stats'!AL45:AN45} -> 43900 | O47: 45726 | P47: 60 | Q47: ='Test 4-Stats'!CX45 -> Active
A48: ='Test 4-Stats'!S46 -> Reg 47 | B48: ='Test 4-Stats'!Y46 -> 2024 | C48: ='Test 4-Stats'!W46 -> ISUZU | D48: ='Test 4-Stats'!V46 -> ONE TON LDV SINGLE CAB | E48: ='Test 4-Stats'!X46 -> D-MAX 250 HO FLEETSIDE (SAFETY) | F48: {='Test 4-Stats'!Z46:AA46} -> DIESEL | G48: 2498 | H48: {='Test 4-Stats'!C46:H46} -> Business Unit 3 | I48: Division 3 | J48: Cost Centre 3 | K48: RICHARDS BAY | L48: KWAZULU NATAL | M48: Manager 2 | N48: {='Test 4-Stats'!AL46:AN46} -> 44023 | O48: 45849 | P48: 60 | Q48: ='Test 4-Stats'!CX46 -> Active
A49: ='Test 4-Stats'!S47 -> Reg 48 | B49: ='Test 4-Stats'!Y47 -> 2024 | C49: ='Test 4-Stats'!W47 -> ISUZU | D49: ='Test 4-Stats'!V47 -> ONE TON LDV SINGLE CAB | E49: ='Test 4-Stats'!X47 -> D-MAX 250 HO FLEETSIDE (SAFETY) | F49: {='Test 4-Stats'!Z47:AA47} -> DIESEL | G49: 2498 | H49: {='Test 4-Stats'!C47:H47} -> Business Unit 1 | I49: Division 1 | J49: Cost Centre 1 | K49: RICHARDS BAY | L49: KWAZULU NATAL | M49: Manager 3 | N49: {='Test 4-Stats'!AL47:AN47} -> 43902 | O49: 45728 | P49: 60 | Q49: ='Test 4-Stats'!CX47 -> Active
... A361: ='Test 4-Stats'!S359 -> Reg 360 | B361: ='Test 4-Stats'!Y359 -> 2021 | C361: ='Test 4-Stats'!W359 -> ISUZU | D361: ='Test 4-Stats'!V359 -> ONE TON LDV SINGLE CAB | E361: ='Test 4-Stats'!X359 -> D-MAX 250 HO FLEETSIDE (SAFETY) | F361: {='Test 4-Stats'!Z359:AA359} -> DIESEL | G361: 2498 | H361: {='Test 4-Stats'!C359:H359} -> Business Unit 1 | I361: Division 1 | J361: Cost Centre 1 | K361: CAPE TOWN | L361: WESTERN CAPE | M361: Manager 3 | N361: {='Test 4-Stats'!AL359:AN359} -> 44699 | O361: 46525 | P361: 60 | Q361: ='Test 4-Stats'!CX359 -> Active

Sheet Fleet Size analysis
A1: FLEET SIZE ANALYSIS DASHBOARD
A3: Fleet Size per Business Unit
A4: Business Unit | B4: Number of Vehicles
A5: Business Unit 1 | B5: 123
A6: Business Unit 2 | B6: 122
A7: Business Unit 3 | B7: 113
A8: Grand Total | B8: 358
A10: Fleet Size per Division/Depot/Department
A11: Division/Depot/Department | B11: Number of Vehicles
A12: Division 1 | B12: 123
A13: Division 2 | B13: 123
A14: Division 3 | B14: 112
A15: Grand Total | B15: 358
A17: Fleet Size per Cost Centre
A18: Cost Centre | B18: Number of Vehicles
A19: Cost Centre 1 | B19: 123
A20: Cost Centre 2 | B20: 123
A21: Cost Centre 3 | B21: 112
A22: Grand Total | B22: 358
A24: Fleet Size per Manager
A25: Manager | B25: Number of Vehicles
A26: Manager 1 | B26: 119
A27: Manager 2 | B27: 120
A28: Manager 3 | B28: 119
A29: (blank)
A30: Grand Total | B30: 358
A32: Fleet Size per Rate Category
A33: Rate Category | B33: Number of Vehicles
A34: ONE TON LDV DOUBLE CAB | B34: 170
A35: ONE TON LDV SINGLE CAB | B35: 83
A36: MINIBUS | B36: 50
A37: SEDAN | B37: 36
A38: HALF TON LDV | B38: 14
A39: ONE TON LDV EXTENDED CAB | B39: 5
A40: Grand Total | B40: 358
A42: Fleet Size per Make
A43: Make | B43: Number of Vehicles
A44: ISUZU | B44: 124
A45: FORD | B45: 102
A46: NISSAN | B46: 63
A47: TOYOTA | B47: 35
A48: HYUNDAI | B48: 14
A49: SUZUKI | B49: 14
A50: VOLKSWAGEN | B50: 4
A51: GWM | B51: 1
A52: MERCEDES | B52: 1
A53: Grand Total | B53: 358
A55: Fleet Size per Model
A56: Model | B56: Number of Vehicles
A57: RANGER 2.0 SiT D CAB BASE 4X2 | B57: 68
A58: D-MAX 250 HO FLEETSIDE (SAFETY) | B58: 49
A59: D-MAX 250 HO HI-RIDER D/CAB | B59: 47
A60: NAVARA 2.5D SE 4X2 S CAB | B60: 22
A61: RANGER 2.0 SiT D CAB BASE 4X4 | B61: 18
A62: ALMERA 1.5 ACENTA | B62: 17
A63: D-MAX 250 HO HI-RIDER D/CAB 4X4 | B63: 12
A64: NP200 1.6 8V AC SAFETY PACK | B64: 12
A65: QUANTUM 2.5 D-4D 14-SEATER BUS | B65: 11
A66: STARIA 2.2D EXECUTIVE 9 SEATER AT | B66: 10
A67: DZIRE 1.2I GA | B67: 9
A68: NAVARA 2.5D SE 4X2 D CAB | B68: 7
... A102: Grand Total | B102: 358
A104: Fleet Size per Year
A105: Year | B105: Number of Vehicles
A106: 2019 | B106: 7
A107: 2020 | B107: 79
A108: 2021 | B108: 30
A109: 2022 | B109: 3
A110: 2023 | B110: 14
A111: 2024 | B111: 224
A112: 2025 | B112: 1
A113: Grand Total | B113: 358
A115: Fleet Size per Fuel Type
A116: Fuel Type | B116: Number of Vehicles
A117: DIESEL | B117: 309
A118: PETROL | B118: 49
A119: Grand Total | B119: 358
A121: Fleet Size per Engine Size
A122: Engine Size | B122: Number of Vehicles
A123: 2498 | B123: 166
A124: 1998 | B124: 94
A125: 1498 | B125: 27
A126: 2198 | B126: 25
A127: 1598 | B127: 13
A128: 2798 | B128: 12
A129: 1198 | B129: 9
A130: 1898 | B130: 6
A131: 2398 | B131: 3
A132: 1798 | B132: 1
A133: 2698 | B133: 1
A134: 2998 | B134: 1
A135: Grand Total | B135: 358
A137: Fleet Size per Province
A138: Province | B138: Number of Vehicles
A139: KWAZULU NATAL | B139: 228
A140: WESTERN CAPE | B140: 99
A141: GAUTENG | B141: 25
A142: MPUMALANGA | B142: 5
A143: FREE STATE | B143: 1
A144: Grand Total | B144: 358
...

Sheet Sheet3

Sheet Sheet4

Sheet Sheet5

Sheet Sheet6

Sheet Sheet7

Sheet Sheet8

Sheet Sheet9

Sheet Sheet10
